{
  "team": "Macau",
  "matches": [
    {
      "date": "1949-01-25",
      "team1": "Macau",
      "team2": "South Korea",
      "score1": 1,
      "score2": 5,
      "rating1": 759.4942700155898,
      "rating2": 1559.6374247979418,
      "rating_ev1": -7.505729984410209,
      "rating_ev2": 7.505729984410209
    },
    {
      "date": "1970-10-30",
      "team1": "Macau",
      "team2": "Australia",
      "score1": 0,
      "score2": 9,
      "rating1": 727.7255562835325,
      "rating2": 1547.0436178885304,
      "rating_ev1": -31.768713732057336,
      "rating_ev2": 31.76871373205745
    },
    {
      "date": "1975-04-04",
      "team1": "Macau",
      "team2": "Panama",
      "score1": 2,
      "score2": 1,
      "rating1": 744.0777245510251,
      "rating2": 1127.8911238523613,
      "rating_ev1": 16.35216826749263,
      "rating_ev2": -16.352168267492743
    },
    {
      "date": "1975-11-05",
      "team1": "Macau",
      "team2": "New Zealand",
      "score1": 1,
      "score2": 1,
      "rating1": 758.1911081881697,
      "rating2": 1319.5470537581862,
      "rating_ev1": 14.11338363714458,
      "rating_ev2": -14.11338363714458
    },
    {
      "date": "1977-05-07",
      "team1": "Hong Kong",
      "team2": "Macau",
      "score1": 2,
      "score2": 0,
      "rating1": 1308.5214028609964,
      "rating2": 763.2147346108364,
      "rating_ev1": -5.023626422666894,
      "rating_ev2": 5.02362642266678
    },
    {
      "date": "1978-06-11",
      "team1": "Macau",
      "team2": "Hong Kong",
      "score1": 0,
      "score2": 4,
      "rating1": 748.491374997532,
      "rating2": 1284.4225684613464,
      "rating_ev1": -14.72335961330441,
      "rating_ev2": 14.72335961330441
    },
    {
      "date": "1978-12-25",
      "team1": "South Korea",
      "team2": "Macau",
      "score1": 4,
      "score2": 1,
      "rating1": 1765.6213180767998,
      "rating2": 762.7198107825806,
      "rating_ev1": -14.228435785048532,
      "rating_ev2": 14.228435785048532
    },
    {
      "date": "1978-12-27",
      "team1": "China PR",
      "team2": "Macau",
      "score1": 2,
      "score2": 1,
      "rating1": 1519.8444306451893,
      "rating2": 792.6837757064696,
      "rating_ev1": -29.96396492388908,
      "rating_ev2": 29.96396492388908
    },
    {
      "date": "1980-06-01",
      "team1": "Macau",
      "team2": "Hong Kong",
      "score1": 0,
      "score2": 2,
      "rating1": 790.1623974581172,
      "rating2": 1280.6343179139828,
      "rating_ev1": -2.5213782483524483,
      "rating_ev2": 2.5213782483524483
    },
    {
      "date": "1980-12-22",
      "team1": "North Korea",
      "team2": "Macau",
      "score1": 3,
      "score2": 0,
      "rating1": 1563.5520010781433,
      "rating2": 792.7553437150575,
      "rating_ev1": -2.592946256940195,
      "rating_ev2": 2.5929462569403086
    },
    {
      "date": "1980-12-24",
      "team1": "China PR",
      "team2": "Macau",
      "score1": 3,
      "score2": 0,
      "rating1": 1564.358468622565,
      "rating2": 795.25653573476,
      "rating_ev1": -2.50119201970233,
      "rating_ev2": 2.5011920197024438
    },
    {
      "date": "1980-12-28",
      "team1": "Japan",
      "team2": "Macau",
      "score1": 3,
      "score2": 0,
      "rating1": 1463.799633373864,
      "rating2": 792.3139438730279,
      "rating_ev1": 2.942591861732126,
      "rating_ev2": -2.942591861732012
    },
    {
      "date": "1981-06-24",
      "team1": "Hong Kong",
      "team2": "Macau",
      "score1": 3,
      "score2": 1,
      "rating1": 1223.4363879700275,
      "rating2": 793.9706533168941,
      "rating_ev1": -1.6567094438660206,
      "rating_ev2": 1.6567094438661343
    },
    {
      "date": "1982-05-09",
      "team1": "Macau",
      "team2": "Hong Kong",
      "score1": 1,
      "score2": 0,
      "rating1": 810.6865171793995,
      "rating2": 1206.7205241075221,
      "rating_ev1": 16.715863862505444,
      "rating_ev2": -16.71586386250533
    },
    {
      "date": "1983-07-01",
      "team1": "Hong Kong",
      "team2": "Macau",
      "score1": 1,
      "score2": 0,
      "rating1": 1224.1974577368337,
      "rating2": 818.8718123679826,
      "rating_ev1": -8.18529518858304,
      "rating_ev2": 8.18529518858304
    },
    {
      "date": "1984-06-17",
      "team1": "Macau",
      "team2": "Hong Kong",
      "score1": 0,
      "score2": 3,
      "rating1": 807.5302351679272,
      "rating2": 1235.1970828041174,
      "rating_ev1": -11.341577200055326,
      "rating_ev2": 11.341577200055326
    },
    {
      "date": "1985-02-17",
      "team1": "Macau",
      "team2": "Brunei",
      "score1": 2,
      "score2": 0,
      "rating1": 804.3993373996997,
      "rating2": 381.138635498753,
      "rating_ev1": -3.1308977682275554,
      "rating_ev2": 3.1308977682275554
    },
    {
      "date": "1985-02-20",
      "team1": "Macau",
      "team2": "China PR",
      "score1": 0,
      "score2": 4,
      "rating1": 792.2033525013179,
      "rating2": 1660.542902504934,
      "rating_ev1": -12.195984898381766,
      "rating_ev2": 12.195984898381766
    },
    {
      "date": "1985-04-13",
      "team1": "Brunei",
      "team2": "Macau",
      "score1": 1,
      "score2": 2,
      "rating1": 353.19476313395467,
      "rating2": 785.7858141755195,
      "rating_ev1": 6.417538325798489,
      "rating_ev2": -6.417538325798432
    },
    {
      "date": "1985-04-28",
      "team1": "Macau",
      "team2": "Hong Kong",
      "score1": 0,
      "score2": 2,
      "rating1": 780.700884628164,
      "rating2": 1275.5347709803825,
      "rating_ev1": -5.0849295473555,
      "rating_ev2": 5.084929547355387
    },
    {
      "date": "1985-05-04",
      "team1": "Hong Kong",
      "team2": "Macau",
      "score1": 2,
      "score2": 0,
      "rating1": 1268.7779697812682,
      "rating2": 787.4576858272782,
      "rating_ev1": -6.756801199114307,
      "rating_ev2": 6.756801199114193
    },
    {
      "date": "1985-05-12",
      "team1": "China PR",
      "team2": "Macau",
      "score1": 6,
      "score2": 0,
      "rating1": 1693.710287094776,
      "rating2": 766.475227332358,
      "rating_ev1": 20.982458494920138,
      "rating_ev2": -20.982458494920138
    },
    {
      "date": "1985-06-01",
      "team1": "Hong Kong",
      "team2": "Macau",
      "score1": 2,
      "score2": 0,
      "rating1": 1308.4451600304694,
      "rating2": 771.2674460264744,
      "rating_ev1": -4.7922186941164,
      "rating_ev2": 4.7922186941164
    },
    {
      "date": "1986-05-31",
      "team1": "Macau",
      "team2": "Hong Kong",
      "score1": 2,
      "score2": 3,
      "rating1": 776.3953042623991,
      "rating2": 1281.0985878782958,
      "rating_ev1": 5.127858235924691,
      "rating_ev2": -5.1278582359245775
    },
    {
      "date": "1987-05-31",
      "team1": "Hong Kong",
      "team2": "Macau",
      "score1": 5,
      "score2": 0,
      "rating1": 1264.6265382955016,
      "rating2": 760.6249193194495,
      "rating_ev1": 15.770384942949477,
      "rating_ev2": -15.77038494294959
    },
    {
      "date": "1988-05-15",
      "team1": "Macau",
      "team2": "Hong Kong",
      "score1": 0,
      "score2": 2,
      "rating1": 758.6137482864676,
      "rating2": 1266.6377093284837,
      "rating_ev1": -2.011171032981906,
      "rating_ev2": 2.01117103298202
    },
    {
      "date": "1989-05-13",
      "team1": "Hong Kong",
      "team2": "Macau",
      "score1": 2,
      "score2": 1,
      "rating1": 1206.4165067229148,
      "rating2": 767.7852203343595,
      "rating_ev1": -9.171472047891712,
      "rating_ev2": 9.171472047891825
    },
    {
      "date": "1992-06-03",
      "team1": "Macau",
      "team2": "Hong Kong",
      "score1": 2,
      "score2": 2,
      "rating1": 792.8047421448521,
      "rating2": 1170.4536375534044,
      "rating_ev1": 25.01952181049262,
      "rating_ev2": -25.019521810492733
    },
    {
      "date": "1992-06-05",
      "team1": "North Korea",
      "team2": "Macau",
      "score1": 2,
      "score2": 0,
      "rating1": 1507.5725991855234,
      "rating2": 812.1228506624695,
      "rating_ev1": -19.318108517617475,
      "rating_ev2": 19.318108517617475
    },
    {
      "date": "1992-06-07",
      "team1": "Macau",
      "team2": "Taiwan",
      "score1": 2,
      "score2": 0,
      "rating1": 847.2143957666585,
      "rating2": 902.1384178836369,
      "rating_ev1": 35.09154510418898,
      "rating_ev2": -35.09154510418898
    },
    {
      "date": "1993-05-01",
      "team1": "Macau",
      "team2": "Saudi Arabia",
      "score1": 0,
      "score2": 6,
      "rating1": 812.8379301186739,
      "rating2": 1605.6860208042,
      "rating_ev1": -34.37646564798467,
      "rating_ev2": 34.37646564798456
    },
    {
      "date": "1993-05-03",
      "team1": "Macau",
      "team2": "Kuwait",
      "score1": 1,
      "score2": 10,
      "rating1": 748.3557989979936,
      "rating2": 1503.5614537596189,
      "rating_ev1": -64.48213112068026,
      "rating_ev2": 64.48213112068015
    },
    {
      "date": "1993-05-05",
      "team1": "Malaysia",
      "team2": "Macau",
      "score1": 9,
      "score2": 0,
      "rating1": 1219.2320667924498,
      "rating2": 677.1569324300403,
      "rating_ev1": 71.19886656795325,
      "rating_ev2": -71.19886656795325
    },
    {
      "date": "1993-05-14",
      "team1": "Saudi Arabia",
      "team2": "Macau",
      "score1": 8,
      "score2": 0,
      "rating1": 1616.6514495440836,
      "rating2": 639.1394356813942,
      "rating_ev1": 38.01749674864618,
      "rating_ev2": -38.01749674864618
    },
    {
      "date": "1993-05-16",
      "team1": "Kuwait",
      "team2": "Macau",
      "score1": 8,
      "score2": 0,
      "rating1": 1563.514341772463,
      "rating2": 594.4815344900977,
      "rating_ev1": 44.65790119129633,
      "rating_ev2": -44.657901191296446
    },
    {
      "date": "1993-05-18",
      "team1": "Macau",
      "team2": "Malaysia",
      "score1": 0,
      "score2": 5,
      "rating1": 564.3625855673822,
      "rating2": 1227.587380675823,
      "rating_ev1": -30.118948922715504,
      "rating_ev2": 30.11894892271539
    },
    {
      "date": "1996-01-30",
      "team1": "China PR",
      "team2": "Macau",
      "score1": 7,
      "score2": 1,
      "rating1": 1498.1688515702708,
      "rating2": 538.7900830317252,
      "rating_ev1": 25.572502535657122,
      "rating_ev2": -25.57250253565701
    },
    {
      "date": "1996-02-01",
      "team1": "Hong Kong",
      "team2": "Macau",
      "score1": 4,
      "score2": 1,
      "rating1": 1204.92468820722,
      "rating2": 541.6636519050278,
      "rating_ev1": -2.8735688733024745,
      "rating_ev2": 2.873568873302588
    },
    {
      "date": "1996-02-04",
      "team1": "Macau",
      "team2": "Philippines",
      "score1": 5,
      "score2": 1,
      "rating1": 595.9761679341229,
      "rating2": 506.0977404416889,
      "rating_ev1": 54.31251602909515,
      "rating_ev2": -54.31251602909521
    },
    {
      "date": "1997-03-23",
      "team1": "Nepal",
      "team2": "Macau",
      "score1": 1,
      "score2": 1,
      "rating1": 514.2524665907107,
      "rating2": 590.7896691964581,
      "rating_ev1": 5.186498737664806,
      "rating_ev2": -5.186498737664806
    },
    {
      "date": "1997-03-25",
      "team1": "Macau",
      "team2": "Japan",
      "score1": 0,
      "score2": 10,
      "rating1": 542.0312897355315,
      "rating2": 1740.0363226943211,
      "rating_ev1": -48.758379460926676,
      "rating_ev2": 48.75837946092656
    },
    {
      "date": "1997-03-27",
      "team1": "Oman",
      "team2": "Macau",
      "score1": 4,
      "score2": 0,
      "rating1": 1262.528185095705,
      "rating2": 534.7433551590922,
      "rating_ev1": 7.287934576439284,
      "rating_ev2": -7.287934576439284
    },
    {
      "date": "1997-06-22",
      "team1": "Japan",
      "team2": "Macau",
      "score1": 10,
      "score2": 0,
      "rating1": 1807.102543298458,
      "rating2": 496.78455420155456,
      "rating_ev1": 37.958800957537505,
      "rating_ev2": -37.95880095753762
    },
    {
      "date": "1997-06-25",
      "team1": "Macau",
      "team2": "Oman",
      "score1": 0,
      "score2": 2,
      "rating1": 513.693118661064,
      "rating2": 1279.8506541174913,
      "rating_ev1": 16.90856445950942,
      "rating_ev2": -16.908564459509535
    },
    {
      "date": "1997-06-28",
      "team1": "Macau",
      "team2": "Nepal",
      "score1": 2,
      "score2": 1,
      "rating1": 528.7239389667391,
      "rating2": 516.6996065334761,
      "rating_ev1": 15.030820305675093,
      "rating_ev2": -15.030820305675093
    },
    {
      "date": "2000-02-13",
      "team1": "Macau",
      "team2": "Brunei",
      "score1": 1,
      "score2": 0,
      "rating1": 529.3566015437256,
      "rating2": 399.26625884964494,
      "rating_ev1": 0.6326625769864904,
      "rating_ev2": -0.6326625769864336
    },
    {
      "date": "2000-02-16",
      "team1": "Macau",
      "team2": "Singapore",
      "score1": 0,
      "score2": 1,
      "rating1": 548.4869300328354,
      "rating2": 1193.0739408801119,
      "rating_ev1": 19.130328489109843,
      "rating_ev2": -19.130328489109843
    },
    {
      "date": "2000-02-20",
      "team1": "Macau",
      "team2": "Japan",
      "score1": 0,
      "score2": 3,
      "rating1": 561.8412888936913,
      "rating2": 1683.8673782900782,
      "rating_ev1": 13.354358860855882,
      "rating_ev2": -13.354358860855882
    },
    {
      "date": "2000-05-28",
      "team1": "Macau",
      "team2": "Hong Kong",
      "score1": 0,
      "score2": 1,
      "rating1": 569.9729325448709,
      "rating2": 1181.0651995297835,
      "rating_ev1": 8.131643651179616,
      "rating_ev2": -8.131643651179502
    },
    {
      "date": "2001-04-12",
      "team1": "Iraq",
      "team2": "Macau",
      "score1": 8,
      "score2": 0,
      "rating1": 1610.1214701993695,
      "rating2": 536.6162925227427,
      "rating_ev1": 33.356640022128204,
      "rating_ev2": -33.356640022128204
    },
    {
      "date": "2001-04-14",
      "team1": "Kazakhstan",
      "team2": "Macau",
      "score1": 3,
      "score2": 0,
      "rating1": 1366.1592911265006,
      "rating2": 542.0464544126636,
      "rating_ev1": -5.430161889920782,
      "rating_ev2": 5.430161889920896
    },
    {
      "date": "2001-04-16",
      "team1": "Nepal",
      "team2": "Macau",
      "score1": 4,
      "score2": 1,
      "rating1": 490.31571410147666,
      "rating2": 495.39289300503924,
      "rating_ev1": 46.65356140762435,
      "rating_ev2": -46.65356140762435
    },
    {
      "date": "2001-04-21",
      "team1": "Macau",
      "team2": "Iraq",
      "score1": 0,
      "score2": 5,
      "rating1": 489.38004638708816,
      "rating2": 1622.335015942391,
      "rating_ev1": -6.012846617951084,
      "rating_ev2": 6.012846617951027
    },
    {
      "date": "2001-04-23",
      "team1": "Kazakhstan",
      "team2": "Macau",
      "score1": 5,
      "score2": 0,
      "rating1": 1396.2825599154648,
      "rating2": 479.4242450745784,
      "rating_ev1": 9.95580131250972,
      "rating_ev2": -9.955801312509777
    },
    {
      "date": "2001-04-25",
      "team1": "Macau",
      "team2": "Nepal",
      "score1": 1,
      "score2": 6,
      "rating1": 417.34914814023836,
      "rating2": 585.3960973034297,
      "rating_ev1": -62.075096934340024,
      "rating_ev2": 62.07509693433997
    },
    {
      "date": "2003-02-22",
      "team1": "Macau",
      "team2": "Mongolia",
      "score1": 2,
      "score2": 0,
      "rating1": 453.0662875816949,
      "rating2": 517.2748438074874,
      "rating_ev1": 35.71713944145654,
      "rating_ev2": -35.71713944145654
    },
    {
      "date": "2003-02-24",
      "team1": "Hong Kong",
      "team2": "Macau",
      "score1": 3,
      "score2": 0,
      "rating1": 1133.9430758219469,
      "rating2": 456.7350492484572,
      "rating_ev1": -3.6687616667622933,
      "rating_ev2": 3.6687616667622933
    },
    {
      "date": "2003-02-26",
      "team1": "Guam",
      "team2": "Macau",
      "score1": 0,
      "score2": 2,
      "rating1": -123.27965024109673,
      "rating2": 450.68676987538436,
      "rating_ev1": 6.048279373072802,
      "rating_ev2": -6.04827937307283
    },
    {
      "date": "2003-03-02",
      "team1": "Macau",
      "team2": "Taiwan",
      "score1": 1,
      "score2": 2,
      "rating1": 455.63362432355063,
      "rating2": 765.9105599510825,
      "rating_ev1": 4.9468544481662775,
      "rating_ev2": -4.9468544481662775
    },
    {
      "date": "2003-03-21",
      "team1": "Macau",
      "team2": "Pakistan",
      "score1": 0,
      "score2": 3,
      "rating1": 421.8834470548051,
      "rating2": 607.332018415452,
      "rating_ev1": -33.75017726874552,
      "rating_ev2": 33.750177268745574
    },
    {
      "date": "2003-03-23",
      "team1": "Singapore",
      "team2": "Macau",
      "score1": 2,
      "score2": 0,
      "rating1": 1036.4799758649506,
      "rating2": 435.8108263758566,
      "rating_ev1": -13.927379321051376,
      "rating_ev2": 13.92737932105149
    },
    {
      "date": "2003-11-23",
      "team1": "Taiwan",
      "team2": "Macau",
      "score1": 3,
      "score2": 0,
      "rating1": 769.2959925557544,
      "rating2": 419.38924941639834,
      "rating_ev1": 16.421576959458207,
      "rating_ev2": -16.421576959458264
    },
    {
      "date": "2003-11-29",
      "team1": "Macau",
      "team2": "Taiwan",
      "score1": 1,
      "score2": 3,
      "rating1": 406.72486907978976,
      "rating2": 781.960372892363,
      "rating_ev1": -12.664380336608588,
      "rating_ev2": 12.664380336608588
    },
    {
      "date": "2005-05-29",
      "team1": "Hong Kong",
      "team2": "Macau",
      "score1": 8,
      "score2": 1,
      "rating1": 1209.4048286001428,
      "rating2": 389.1502061737053,
      "rating_ev1": 17.57466290608454,
      "rating_ev2": -17.574662906084427
    },
    {
      "date": "2006-04-02",
      "team1": "Tajikistan",
      "team2": "Macau",
      "score1": 4,
      "score2": 0,
      "rating1": 1323.1240551144137,
      "rating2": 386.620037336393,
      "rating_ev1": 2.5301688373124307,
      "rating_ev2": -2.530168837312317
    },
    {
      "date": "2006-04-06",
      "team1": "Pakistan",
      "team2": "Macau",
      "score1": 2,
      "score2": 2,
      "rating1": 700.7246012941695,
      "rating2": 406.3044446297166,
      "rating_ev1": -19.684407293323602,
      "rating_ev2": 19.684407293323602
    },
    {
      "date": "2006-04-07",
      "team1": "Macau",
      "team2": "Kyrgyzstan",
      "score1": 0,
      "score2": 2,
      "rating1": 419.908177127819,
      "rating2": 1125.3155507399538,
      "rating_ev1": 13.603732498102374,
      "rating_ev2": -13.603732498102318
    },
    {
      "date": "2006-06-03",
      "team1": "Macau",
      "team2": "Hong Kong",
      "score1": 0,
      "score2": 0,
      "rating1": 437.73490977660214,
      "rating2": 1135.8637397855427,
      "rating_ev1": 17.82673264878315,
      "rating_ev2": -17.826732648783263
    },
    {
      "date": "2006-08-09",
      "team1": "Macau",
      "team2": "Taiwan",
      "score1": 0,
      "score2": 1,
      "rating1": 435.24417861333114,
      "rating2": 686.5944990755786,
      "rating_ev1": -2.4907311632709934,
      "rating_ev2": 2.4907311632709934
    },
    {
      "date": "2007-06-10",
      "team1": "Hong Kong",
      "team2": "Macau",
      "score1": 2,
      "score2": 1,
      "rating1": 1144.9123159960488,
      "rating2": 451.53994117982865,
      "rating_ev1": -16.295762566497615,
      "rating_ev2": 16.2957625664975
    },
    {
      "date": "2007-06-17",
      "team1": "Macau",
      "team2": "Mongolia",
      "score1": 0,
      "score2": 0,
      "rating1": 438.2095832287361,
      "rating2": 335.88529074273487,
      "rating_ev1": -13.330357951092537,
      "rating_ev2": 13.330357951092537
    },
    {
      "date": "2007-06-21",
      "team1": "Macau",
      "team2": "North Korea",
      "score1": 1,
      "score2": 7,
      "rating1": 415.9205050846345,
      "rating2": 1577.795528035359,
      "rating_ev1": -22.28907814410161,
      "rating_ev2": 22.289078144101723
    },
    {
      "date": "2007-10-08",
      "team1": "Thailand",
      "team2": "Macau",
      "score1": 6,
      "score2": 1,
      "rating1": 1377.151627345794,
      "rating2": 408.5257099349632,
      "rating_ev1": 7.394795149671381,
      "rating_ev2": -7.3947951496713245
    },
    {
      "date": "2007-10-15",
      "team1": "Macau",
      "team2": "Thailand",
      "score1": 1,
      "score2": 7,
      "rating1": 380.0101221853828,
      "rating2": 1405.6672150953743,
      "rating_ev1": -28.51558774958039,
      "rating_ev2": 28.51558774958039
    },
    {
      "date": "2008-05-24",
      "team1": "Nepal",
      "team2": "Macau",
      "score1": 3,
      "score2": 2,
      "rating1": 574.4234436920419,
      "rating2": 377.468390670362,
      "rating_ev1": 2.5417315150207287,
      "rating_ev2": -2.5417315150207855
    },
    {
      "date": "2008-05-28",
      "team1": "Cambodia",
      "team2": "Macau",
      "score1": 3,
      "score2": 1,
      "rating1": 508.79725267499646,
      "rating2": 362.41077058697147,
      "rating_ev1": 15.057620083390532,
      "rating_ev2": -15.057620083390532
    },
    {
      "date": "2008-06-15",
      "team1": "Macau",
      "team2": "Hong Kong",
      "score1": 0,
      "score2": 1,
      "rating1": 374.90094051863093,
      "rating2": 1150.5956150088246,
      "rating_ev1": 12.490169931659466,
      "rating_ev2": -12.490169931659466
    },
    {
      "date": "2008-11-19",
      "team1": "Macau",
      "team2": "Hong Kong",
      "score1": 1,
      "score2": 9,
      "rating1": 347.2791810346422,
      "rating2": 1178.2173744928132,
      "rating_ev1": -27.62175948398874,
      "rating_ev2": 27.621759483988626
    },
    {
      "date": "2009-03-11",
      "team1": "Macau",
      "team2": "Northern Mariana Islands",
      "score1": 6,
      "score2": 1,
      "rating1": 406.0702887350945,
      "rating2": 189.50743319083074,
      "rating_ev1": 58.7911077004523,
      "rating_ev2": -58.7911077004523
    },
    {
      "date": "2009-03-13",
      "team1": "Macau",
      "team2": "Mongolia",
      "score1": 1,
      "score2": 2,
      "rating1": 386.1042961452209,
      "rating2": 325.25500280408187,
      "rating_ev1": -19.965992589873565,
      "rating_ev2": 19.965992589873565
    },
    {
      "date": "2009-03-15",
      "team1": "Guam",
      "team2": "Macau",
      "score1": 2,
      "score2": 2,
      "rating1": -182.48516825110076,
      "rating2": 357.47266619747444,
      "rating_ev1": 28.63162994774649,
      "rating_ev2": -28.63162994774649
    },
    {
      "date": "2009-04-07",
      "team1": "Macau",
      "team2": "Mongolia",
      "score1": 2,
      "score2": 0,
      "rating1": 379.37330181196126,
      "rating2": 334.050418791018,
      "rating_ev1": 21.900635614486816,
      "rating_ev2": -21.900635614486816
    },
    {
      "date": "2009-04-14",
      "team1": "Mongolia",
      "team2": "Macau",
      "score1": 3,
      "score2": 1,
      "rating1": 358.74836491031533,
      "rating2": 354.6753556926639,
      "rating_ev1": 24.69794611929734,
      "rating_ev2": -24.69794611929734
    },
    {
      "date": "2009-04-26",
      "team1": "Myanmar",
      "team2": "Macau",
      "score1": 4,
      "score2": 0,
      "rating1": 1015.5027712301435,
      "rating2": 338.22715891253625,
      "rating_ev1": 16.44819678012766,
      "rating_ev2": -16.44819678012766
    },
    {
      "date": "2009-04-28",
      "team1": "Macau",
      "team2": "Cambodia",
      "score1": 1,
      "score2": 2,
      "rating1": 331.8895698056195,
      "rating2": 472.3138056953958,
      "rating_ev1": -6.3375891069167665,
      "rating_ev2": 6.3375891069167665
    },
    {
      "date": "2009-04-30",
      "team1": "Bangladesh",
      "team2": "Macau",
      "score1": 3,
      "score2": 0,
      "rating1": 746.8028705919306,
      "rating2": 320.4003895635669,
      "rating_ev1": 11.489180242052612,
      "rating_ev2": -11.489180242052612
    },
    {
      "date": "2010-10-12",
      "team1": "Philippines",
      "team2": "Macau",
      "score1": 5,
      "score2": 0,
      "rating1": 619.7673659069065,
      "rating2": 270.49810195612633,
      "rating_ev1": 49.902287607440485,
      "rating_ev2": -49.90228760744054
    },
    {
      "date": "2011-02-09",
      "team1": "Cambodia",
      "team2": "Macau",
      "score1": 3,
      "score2": 1,
      "rating1": 526.8352281091826,
      "rating2": 263.2805191847281,
      "rating_ev1": 7.21758277139827,
      "rating_ev2": -7.217582771398213
    },
    {
      "date": "2011-02-16",
      "team1": "Macau",
      "team2": "Cambodia",
      "score1": 3,
      "score2": 2,
      "rating1": 287.20982545286444,
      "rating2": 502.9059218410463,
      "rating_ev1": 23.929306268136315,
      "rating_ev2": -23.929306268136315
    },
    {
      "date": "2011-06-29",
      "team1": "Vietnam",
      "team2": "Macau",
      "score1": 6,
      "score2": 0,
      "rating1": 1241.269593623185,
      "rating2": 268.5017038593637,
      "rating_ev1": 18.708121593500664,
      "rating_ev2": -18.70812159350072
    },
    {
      "date": "2011-07-03",
      "team1": "Macau",
      "team2": "Vietnam",
      "score1": 1,
      "score2": 7,
      "rating1": 240.16761634310615,
      "rating2": 1269.6036811394426,
      "rating_ev1": -28.33408751625757,
      "rating_ev2": 28.33408751625757
    },
    {
      "date": "2011-10-02",
      "team1": "Hong Kong",
      "team2": "Macau",
      "score1": 5,
      "score2": 1,
      "rating1": 1062.3299075740802,
      "rating2": 232.1992158813404,
      "rating_ev1": 7.968400461765668,
      "rating_ev2": -7.968400461765754
    },
    {
      "date": "2011-10-04",
      "team1": "Philippines",
      "team2": "Macau",
      "score1": 2,
      "score2": 0,
      "rating1": 917.4912193276637,
      "rating2": 244.01716545590483,
      "rating_ev1": -11.817949574564409,
      "rating_ev2": 11.817949574564437
    },
    {
      "date": "2012-07-20",
      "team1": "Northern Mariana Islands",
      "team2": "Macau",
      "score1": 1,
      "score2": 5,
      "rating1": 29.918690734980075,
      "rating2": 287.0254190375845,
      "rating_ev1": -43.008253581679696,
      "rating_ev2": 43.008253581679696
    },
    {
      "date": "2012-07-22",
      "team1": "Guam",
      "team2": "Macau",
      "score1": 3,
      "score2": 0,
      "rating1": -72.15289354873192,
      "rating2": 227.35996606333723,
      "rating_ev1": 59.6654529742473,
      "rating_ev2": -59.6654529742473
    },
    {
      "date": "2012-09-27",
      "team1": "Philippines",
      "team2": "Macau",
      "score1": 5,
      "score2": 0,
      "rating1": 1001.1927962303158,
      "rating2": 219.2699986021527,
      "rating_ev1": 8.089967461184528,
      "rating_ev2": -8.089967461184528
    },
    {
      "date": "2012-09-29",
      "team1": "Macau",
      "team2": "Guam",
      "score1": 0,
      "score2": 3,
      "rating1": 190.97328399041294,
      "rating2": -19.296007466036517,
      "rating_ev1": -28.29671461173976,
      "rating_ev2": 28.296714611739763
    },
    {
      "date": "2013-03-17",
      "team1": "Kyrgyzstan",
      "team2": "Macau",
      "score1": 1,
      "score2": 0,
      "rating1": 935.9437182608899,
      "rating2": 226.2452824703426,
      "rating_ev1": -35.27199847992972,
      "rating_ev2": 35.271998479929664
    },
    {
      "date": "2013-03-19",
      "team1": "Macau",
      "team2": "Tajikistan",
      "score1": 0,
      "score2": 3,
      "rating1": 237.25792196304275,
      "rating2": 1172.1400524619296,
      "rating_ev1": 11.012639492700146,
      "rating_ev2": -11.012639492700146
    },
    {
      "date": "2013-03-21",
      "team1": "Pakistan",
      "team2": "Macau",
      "score1": 2,
      "score2": 0,
      "rating1": 762.7945753177736,
      "rating2": 240.212294680611,
      "rating_ev1": -2.954372717568276,
      "rating_ev2": 2.9543727175682477
    },
    {
      "date": "2014-07-21",
      "team1": "Guam",
      "team2": "Macau",
      "score1": 0,
      "score2": 0,
      "rating1": 98.36738993262901,
      "rating2": 237.22348856043155,
      "rating_ev1": 2.988806120179433,
      "rating_ev2": -2.988806120179447
    },
    {
      "date": "2014-07-23",
      "team1": "Northern Mariana Islands",
      "team2": "Macau",
      "score1": 2,
      "score2": 1,
      "rating1": -71.90641939586351,
      "rating2": 203.03858044106744,
      "rating_ev1": 34.18490811936411,
      "rating_ev2": -34.18490811936411
    },
    {
      "date": "2014-07-25",
      "team1": "Macau",
      "team2": "Mongolia",
      "score1": 3,
      "score2": 2,
      "rating1": 229.0472767864383,
      "rating2": 379.8191993360737,
      "rating_ev1": 26.00869634537085,
      "rating_ev2": -26.008696345370822
    },
    {
      "date": "2014-10-14",
      "team1": "Macau",
      "team2": "Singapore",
      "score1": 2,
      "score2": 2,
      "rating1": 249.893895036692,
      "rating2": 1066.984008011126,
      "rating_ev1": 20.846618250253698,
      "rating_ev2": -20.84661825025364
    },
    {
      "date": "2015-03-12",
      "team1": "Cambodia",
      "team2": "Macau",
      "score1": 3,
      "score2": 0,
      "rating1": 423.09235475255826,
      "rating2": 223.49770490480148,
      "rating_ev1": 26.396190131890535,
      "rating_ev2": -26.396190131890506
    },
    {
      "date": "2015-03-17",
      "team1": "Macau",
      "team2": "Cambodia",
      "score1": 1,
      "score2": 1,
      "rating1": 229.7236916413507,
      "rating2": 416.866368016009,
      "rating_ev1": 6.225986736549231,
      "rating_ev2": -6.22598673654926
    },
    {
      "date": "2015-11-14",
      "team1": "Hong Kong",
      "team2": "Macau",
      "score1": 2,
      "score2": 0,
      "rating1": 1069.6058013356276,
      "rating2": 242.24569228812592,
      "rating_ev1": -12.522000646775268,
      "rating_ev2": 12.522000646775211
    },
    {
      "date": "2016-03-29",
      "team1": "Malaysia",
      "team2": "Macau",
      "score1": 0,
      "score2": 0,
      "rating1": 927.324205982233,
      "rating2": 265.0642967963189,
      "rating_ev1": -22.818604508192948,
      "rating_ev2": 22.818604508192976
    },
    {
      "date": "2016-06-30",
      "team1": "Macau",
      "team2": "Mongolia",
      "score1": 2,
      "score2": 2,
      "rating1": 276.5788537565445,
      "rating2": 447.16414866256883,
      "rating_ev1": 11.514556960225605,
      "rating_ev2": -11.514556960225605
    },
    {
      "date": "2016-07-02",
      "team1": "Northern Mariana Islands",
      "team2": "Macau",
      "score1": 1,
      "score2": 3,
      "rating1": -122.7741401175887,
      "rating2": 281.0403852764997,
      "rating_ev1": -4.461531519955216,
      "rating_ev2": 4.4615315199552015
    },
    {
      "date": "2016-11-03",
      "team1": "Macau",
      "team2": "Mongolia",
      "score1": 2,
      "score2": 1,
      "rating1": 307.60440191195136,
      "rating2": 466.70233057867586,
      "rating_ev1": 26.56401663545165,
      "rating_ev2": -26.56401663545165
    },
    {
      "date": "2016-11-06",
      "team1": "Laos",
      "team2": "Macau",
      "score1": 1,
      "score2": 4,
      "rating1": 458.9648709828697,
      "rating2": 360.5315663569703,
      "rating_ev1": -52.927164445018946,
      "rating_ev2": 52.927164445018946
    },
    {
      "date": "2016-11-09",
      "team1": "Sri Lanka",
      "team2": "Macau",
      "score1": 1,
      "score2": 1,
      "rating1": 426.28469265398576,
      "rating2": 364.70587351328584,
      "rating_ev1": -4.174307156315535,
      "rating_ev2": 4.174307156315535
    },
    {
      "date": "2016-11-12",
      "team1": "Macau",
      "team2": "Brunei",
      "score1": 1,
      "score2": 1,
      "rating1": 363.0268882599345,
      "rating2": 338.27201295291627,
      "rating_ev1": -1.6789852533513567,
      "rating_ev2": 1.6789852533513567
    },
    {
      "date": "2016-11-15",
      "team1": "Nepal",
      "team2": "Macau",
      "score1": 1,
      "score2": 0,
      "rating1": 707.583417492137,
      "rating2": 369.7618474769587,
      "rating_ev1": -6.734959217024198,
      "rating_ev2": 6.734959217024198
    },
    {
      "date": "2017-03-28",
      "team1": "Kyrgyzstan",
      "team2": "Macau",
      "score1": 1,
      "score2": 0,
      "rating1": 1084.9774784044055,
      "rating2": 403.4972477217459,
      "rating_ev1": -33.73540024478734,
      "rating_ev2": 33.73540024478723
    },
    {
      "date": "2017-06-13",
      "team1": "Macau",
      "team2": "Myanmar",
      "score1": 0,
      "score2": 4,
      "rating1": 374.7219355136807,
      "rating2": 951.0515716218305,
      "rating_ev1": -28.775312208065202,
      "rating_ev2": 28.775312208065202
    },
    {
      "date": "2017-09-05",
      "team1": "Macau",
      "team2": "India",
      "score1": 0,
      "score2": 2,
      "rating1": 379.2404526259171,
      "rating2": 1034.8497477220826,
      "rating_ev1": 4.518517112236395,
      "rating_ev2": -4.518517112236395
    },
    {
      "date": "2017-10-02",
      "team1": "Macau",
      "team2": "Laos",
      "score1": 3,
      "score2": 1,
      "rating1": 394.42618526326015,
      "rating2": 504.67517738290616,
      "rating_ev1": 15.185732637343051,
      "rating_ev2": -15.185732637343051
    },
    {
      "date": "2017-10-11",
      "team1": "India",
      "team2": "Macau",
      "score1": 4,
      "score2": 1,
      "rating1": 1033.45332748939,
      "rating2": 395.82260549595276,
      "rating_ev1": -1.3964202326926625,
      "rating_ev2": 1.3964202326926056
    },
    {
      "date": "2017-11-14",
      "team1": "Macau",
      "team2": "Kyrgyzstan",
      "score1": 3,
      "score2": 4,
      "rating1": 414.58140269527996,
      "rating2": 1052.644208546078,
      "rating_ev1": 18.758797199327205,
      "rating_ev2": -18.75879719932732
    },
    {
      "date": "2018-03-22",
      "team1": "Macau",
      "team2": "Mauritius",
      "score1": 0,
      "score2": 1,
      "rating1": 421.050803789605,
      "rating2": 972.6776811608281,
      "rating_ev1": 6.469401094325065,
      "rating_ev2": -6.469401094325008
    },
    {
      "date": "2018-03-27",
      "team1": "Myanmar",
      "team2": "Macau",
      "score1": 1,
      "score2": 0,
      "rating1": 895.9636220569671,
      "rating2": 441.5165529646123,
      "rating_ev1": -20.465749175007318,
      "rating_ev2": 20.46574917500726
    },
    {
      "date": "2018-08-29",
      "team1": "Macau",
      "team2": "Solomon Islands",
      "score1": 1,
      "score2": 4,
      "rating1": 439.27040159006503,
      "rating2": 1190.3829769810766,
      "rating_ev1": -2.246151374547253,
      "rating_ev2": 2.246151374547253
    },
    {
      "date": "2018-09-02",
      "team1": "Mongolia",
      "team2": "Macau",
      "score1": 4,
      "score2": 1,
      "rating1": 507.39905520105236,
      "rating2": 406.2226968041536,
      "rating_ev1": 33.047704785911435,
      "rating_ev2": -33.047704785911435
    },
    {
      "date": "2018-09-04",
      "team1": "Macau",
      "team2": "Guam",
      "score1": 2,
      "score2": 0,
      "rating1": 444.05420608472906,
      "rating2": 539.7243328046371,
      "rating_ev1": 37.83150928057546,
      "rating_ev2": -37.83150928057546
    },
    {
      "date": "2018-09-06",
      "team1": "Northern Mariana Islands",
      "team2": "Macau",
      "score1": 1,
      "score2": 1,
      "rating1": -210.44877359630337,
      "rating2": 404.77247003968137,
      "rating_ev1": 39.28173604504772,
      "rating_ev2": -39.281736045047694
    },
    {
      "date": "2019-06-06",
      "team1": "Macau",
      "team2": "Sri Lanka",
      "score1": 1,
      "score2": 0,
      "rating1": 416.4636865990502,
      "rating2": 449.67015866671176,
      "rating_ev1": 11.691216559368854,
      "rating_ev2": -11.691216559368854
    },
    {
      "date": "2019-06-11",
      "team1": "Sri Lanka",
      "team2": "Macau",
      "score1": 3,
      "score2": 0,
      "rating1": 482.8297779879066,
      "rating2": 383.3040672778554,
      "rating_ev1": 33.15961932119484,
      "rating_ev2": -33.15961932119484
    },
    {
      "date": "2023-03-26",
      "team1": "Macau",
      "team2": "Singapore",
      "score1": 0,
      "score2": 1,
      "rating1": 392.587926386707,
      "rating2": 1045.8721774374542,
      "rating_ev1": 9.28385910885163,
      "rating_ev2": -9.28385910885163
    },
    {
      "date": "2023-06-19",
      "team1": "Macau",
      "team2": "Myanmar",
      "score1": 0,
      "score2": 2,
      "rating1": 388.00115925190573,
      "rating2": 709.6969867185304,
      "rating_ev1": -4.586767134801278,
      "rating_ev2": 4.586767134801335
    },
    {
      "date": "2023-09-06",
      "team1": "Macau",
      "team2": "Bhutan",
      "score1": 0,
      "score2": 1,
      "rating1": 372.1582943677445,
      "rating2": 200.44320601385735,
      "rating_ev1": -15.842864884161258,
      "rating_ev2": 15.842864884161258
    },
    {
      "date": "2023-09-11",
      "team1": "Cambodia",
      "team2": "Macau",
      "score1": 4,
      "score2": 0,
      "rating1": 606.678764263474,
      "rating2": 354.83370878075084,
      "rating_ev1": 17.324585586993635,
      "rating_ev2": -17.324585586993635
    },
    {
      "date": "2023-10-12",
      "team1": "Myanmar",
      "team2": "Macau",
      "score1": 5,
      "score2": 1,
      "rating1": 738.8753380948975,
      "rating2": 328.3275505807666,
      "rating_ev1": 26.506158199984156,
      "rating_ev2": -26.506158199984213
    },
    {
      "date": "2023-10-17",
      "team1": "Macau",
      "team2": "Myanmar",
      "score1": 0,
      "score2": 0,
      "rating1": 346.74208638203265,
      "rating2": 720.4608022936314,
      "rating_ev1": 18.414535801266027,
      "rating_ev2": -18.414535801266084
    }
  ]
}