{
  "team": "Vanuatu",
  "matches": [
    {
      "date": "2023-12-01",
      "country": "Solomon Islands",
      "tournament": "Pacific Games",
      "team1": "Vanuatu",
      "team2": "Fiji",
      "original_team1": "Vanuatu",
      "original_team2": "Fiji",
      "flag1": "vanuatu.png",
      "flag2": "fiji.png",
      "score1": 2,
      "score2": 4,
      "rating1": 4354.511381101138,
      "rating2": 4493.629008576943,
      "rating_ev": -21.951450644771285,
      "win_prob": 39.7
    },
    {
      "date": "2023-11-28",
      "country": "Solomon Islands",
      "tournament": "Pacific Games",
      "team1": "Vanuatu",
      "team2": "New Caledonia",
      "original_team1": "Vanuatu",
      "original_team2": "New Caledonia",
      "flag1": "vanuatu.png",
      "flag2": "caledonia.png",
      "score1": 0,
      "score2": 1,
      "rating1": 4376.462831745909,
      "rating2": 4537.290091287217,
      "rating_ev": -4.964146152159628,
      "win_prob": 34.0
    },
    {
      "date": "2023-11-23",
      "country": "Solomon Islands",
      "tournament": "Pacific Games",
      "team1": "Vanuatu",
      "team2": "Papua New Guinea",
      "original_team1": "Vanuatu",
      "original_team2": "Papua New Guinea",
      "flag1": "vanuatu.png",
      "flag2": "papua.png",
      "score1": 1,
      "score2": 1,
      "rating1": 4381.426977898069,
      "rating2": 4391.693268878536,
      "rating_ev": 0.6963649952613196,
      "win_prob": 48.7
    },
    {
      "date": "2023-11-20",
      "country": "Solomon Islands",
      "tournament": "Pacific Games",
      "team1": "Vanuatu",
      "team2": "Tuvalu",
      "original_team1": "Vanuatu",
      "original_team2": "Tuvalu",
      "flag1": "vanuatu.png",
      "flag2": "tuvalu.png",
      "score1": 6,
      "score2": 0,
      "rating1": 4380.7306129028075,
      "rating2": 3059.3176012109134,
      "rating_ev": 9.745184840325237,
      "win_prob": 99.2
    },
    {
      "date": "2023-10-14",
      "country": "New Caledonia",
      "tournament": "Melanesian Cup",
      "team1": "Vanuatu",
      "team2": "Papua New Guinea",
      "original_team1": "Vanuatu",
      "original_team2": "Papua New Guinea",
      "flag1": "vanuatu.png",
      "flag2": "papua.png",
      "score1": 1,
      "score2": 0,
      "rating1": 4370.985428062482,
      "rating2": 4392.389633873798,
      "rating_ev": 17.296999168913317,
      "win_prob": 43.9
    },
    {
      "date": "2023-10-11",
      "country": "New Caledonia",
      "tournament": "Melanesian Cup",
      "team1": "Vanuatu",
      "team2": "Solomon Islands",
      "original_team1": "Vanuatu",
      "original_team2": "Solomon Islands",
      "flag1": "vanuatu.png",
      "flag2": "solomon.png",
      "score1": 0,
      "score2": 1,
      "rating1": 4353.688428893569,
      "rating2": 4525.242318654908,
      "rating_ev": -4.243544897209176,
      "win_prob": 32.8
    },
    {
      "date": "2023-10-08",
      "country": "New Caledonia",
      "tournament": "Melanesian Cup",
      "team1": "Vanuatu",
      "team2": "New Caledonia",
      "original_team1": "Vanuatu",
      "original_team2": "New Caledonia",
      "flag1": "vanuatu.png",
      "flag2": "caledonia.png",
      "score1": 0,
      "score2": 4,
      "rating1": 4357.931973790778,
      "rating2": 4488.102061960486,
      "rating_ev": -45.173716288431024,
      "win_prob": 35.1
    },
    {
      "date": "2023-06-15",
      "country": "India",
      "tournament": "Friendly tournament",
      "team1": "Vanuatu",
      "team2": "Mongolia",
      "original_team1": "Vanuatu",
      "original_team2": "Mongolia",
      "flag1": "vanuatu.png",
      "flag2": "mongolia.png",
      "score1": 1,
      "score2": 0,
      "rating1": 4403.105690079209,
      "rating2": 4100.5259505270415,
      "rating_ev": -4.444654837074268,
      "win_prob": 79.5
    },
    {
      "date": "2023-06-12",
      "country": "India",
      "tournament": "Friendly tournament",
      "team1": "Vanuatu",
      "team2": "India",
      "original_team1": "Vanuatu",
      "original_team2": "India",
      "flag1": "vanuatu.png",
      "flag2": "india.png",
      "score1": 0,
      "score2": 1,
      "rating1": 4407.550344916283,
      "rating2": 4565.163319429741,
      "rating_ev": 1.2189627476955138,
      "win_prob": 24.2
    },
    {
      "date": "2023-06-09",
      "country": "India",
      "tournament": "Friendly tournament",
      "team1": "Vanuatu",
      "team2": "Lebanon",
      "original_team1": "Vanuatu",
      "original_team2": "Lebanon",
      "flag1": "vanuatu.png",
      "flag2": "lebanon.png",
      "score1": 1,
      "score2": 3,
      "rating1": 4406.331382168588,
      "rating2": 4777.6806811901015,
      "rating_ev": -6.545566501285975,
      "win_prob": 17.4
    },
    {
      "date": "2023-03-23",
      "country": "Fiji",
      "tournament": "Friendly tournament",
      "team1": "Vanuatu",
      "team2": "Solomon Islands",
      "original_team1": "Vanuatu",
      "original_team2": "Solomon Islands",
      "flag1": "vanuatu.png",
      "flag2": "solomon.png",
      "score1": 0,
      "score2": 2,
      "rating1": 4412.876948669874,
      "rating2": 4473.984466829701,
      "rating_ev": -27.236246725394267,
      "win_prob": 49.3
    },
    {
      "date": "2023-03-20",
      "country": "Fiji",
      "tournament": "Friendly tournament",
      "team1": "Vanuatu",
      "team2": "Fiji",
      "original_team1": "Vanuatu",
      "original_team2": "Fiji",
      "flag1": "vanuatu.png",
      "flag2": "fiji.png",
      "score1": 2,
      "score2": 1,
      "rating1": 4440.113195395268,
      "rating2": 4507.8163769606945,
      "rating_ev": 26.831244813925878,
      "win_prob": 27.4
    },
    {
      "date": "2022-09-24",
      "country": "Vanuatu",
      "tournament": "Melanesian Cup",
      "team1": "Vanuatu",
      "team2": "Papua New Guinea",
      "original_team1": "Vanuatu",
      "original_team2": "Papua New Guinea",
      "flag1": "vanuatu.png",
      "flag2": "papua.png",
      "score1": 0,
      "score2": 1,
      "rating1": 4413.281950581342,
      "rating2": 4481.231134101096,
      "rating_ev": -17.643978602409334,
      "win_prob": 57.3
    },
    {
      "date": "2022-03-28",
      "country": "Qatar",
      "tournament": "Friendly",
      "team1": "Vanuatu",
      "team2": "Fiji",
      "original_team1": "Vanuatu",
      "original_team2": "Fiji",
      "flag1": "vanuatu.png",
      "flag2": "fiji.png",
      "score1": 1,
      "score2": 2,
      "rating1": 4430.925929183752,
      "rating2": 4539.216358187174,
      "rating_ev": -3.9841896072484815,
      "win_prob": 39.1
    },
    {
      "date": "2022-03-10",
      "country": "Qatar",
      "tournament": "Friendly",
      "team1": "Vanuatu",
      "team2": "Fiji",
      "original_team1": "Vanuatu",
      "original_team2": "Fiji",
      "flag1": "vanuatu.png",
      "flag2": "fiji.png",
      "score1": 0,
      "score2": 3,
      "rating1": 4434.910118791,
      "rating2": 4576.904760322293,
      "rating_ev": -17.181853291755942,
      "win_prob": 38.4
    },
    {
      "date": "2019-07-18",
      "country": "Samoa",
      "tournament": "Pacific Games",
      "team1": "Vanuatu",
      "team2": "Samoa",
      "original_team1": "Vanuatu",
      "original_team2": "Samoa",
      "flag1": "vanuatu.png",
      "flag2": "samoa.png",
      "score1": 11,
      "score2": 0,
      "rating1": 4452.091972082756,
      "rating2": 3186.7052047621364,
      "rating_ev": 30.39023768138395,
      "win_prob": 98.4
    },
    {
      "date": "2019-07-15",
      "country": "Samoa",
      "tournament": "Pacific Games",
      "team1": "Vanuatu",
      "team2": "Tonga",
      "original_team1": "Vanuatu",
      "original_team2": "Tonga",
      "flag1": "vanuatu.png",
      "flag2": "tonga.png",
      "score1": 14,
      "score2": 0,
      "rating1": 4421.701734401372,
      "rating2": 3077.131668588681,
      "rating_ev": 35.563460498755376,
      "win_prob": 99.1
    },
    {
      "date": "2019-07-10",
      "country": "Samoa",
      "tournament": "Pacific Games",
      "team1": "Vanuatu",
      "team2": "Papua New Guinea",
      "original_team1": "Vanuatu",
      "original_team2": "Papua New Guinea",
      "flag1": "vanuatu.png",
      "flag2": "papua.png",
      "score1": 0,
      "score2": 2,
      "rating1": 4386.138273902617,
      "rating2": 4388.127834979926,
      "rating_ev": -31.24456953245044,
      "win_prob": 56.6
    },
    {
      "date": "2019-06-15",
      "country": "Indonesia",
      "tournament": "Friendly",
      "team1": "Vanuatu",
      "team2": "Indonesia",
      "original_team1": "Vanuatu",
      "original_team2": "Indonesia",
      "flag1": "vanuatu.png",
      "flag2": "indonesia.png",
      "score1": 0,
      "score2": 6,
      "rating1": 4417.382843435067,
      "rating2": 4583.1095066364405,
      "rating_ev": -31.722044686243862,
      "win_prob": 29.1
    },
    {
      "date": "2019-06-10",
      "country": "Vanuatu",
      "tournament": "Friendly tournament",
      "team1": "Vanuatu",
      "team2": "Fiji",
      "original_team1": "Vanuatu",
      "original_team2": "Fiji",
      "flag1": "vanuatu.png",
      "flag2": "fiji.png",
      "score1": 0,
      "score2": 0,
      "rating1": 4449.104888121311,
      "rating2": 4540.502898747954,
      "rating_ev": -0.2125277368049865,
      "win_prob": 51.0
    },
    {
      "date": "2019-06-04",
      "country": "Vanuatu",
      "tournament": "Friendly tournament",
      "team1": "Vanuatu",
      "team2": "Tahiti",
      "original_team1": "Vanuatu",
      "original_team2": "Tahiti",
      "flag1": "vanuatu.png",
      "flag2": "tahiti.png",
      "score1": 2,
      "score2": 0,
      "rating1": 4449.317415858116,
      "rating2": 4393.602907903445,
      "rating_ev": 21.195775110235445,
      "win_prob": 62.2
    },
    {
      "date": "2019-03-18",
      "country": "Solomon Islands",
      "tournament": "Friendly",
      "team1": "Vanuatu",
      "team2": "Solomon Islands",
      "original_team1": "Vanuatu",
      "original_team2": "Solomon Islands",
      "flag1": "vanuatu.png",
      "flag2": "solomon.png",
      "score1": 1,
      "score2": 3,
      "rating1": 4428.1216407478805,
      "rating2": 4477.375013644119,
      "rating_ev": -10.129976711536074,
      "win_prob": 36.2
    },
    {
      "date": "2018-11-17",
      "country": "Vanuatu",
      "tournament": "Friendly",
      "team1": "Vanuatu",
      "team2": "New Caledonia",
      "original_team1": "Vanuatu",
      "original_team2": "New Caledonia",
      "flag1": "vanuatu.png",
      "flag2": "caledonia.png",
      "score1": 2,
      "score2": 2,
      "rating1": 4438.251617459417,
      "rating2": 4478.646600792112,
      "rating_ev": -1.7168665756789778,
      "win_prob": 56.9
    },
    {
      "date": "2018-11-14",
      "country": "Vanuatu",
      "tournament": "Friendly",
      "team1": "Vanuatu",
      "team2": "New Caledonia",
      "original_team1": "Vanuatu",
      "original_team2": "New Caledonia",
      "flag1": "vanuatu.png",
      "flag2": "caledonia.png",
      "score1": 0,
      "score2": 1,
      "rating1": 4439.968484035096,
      "rating2": 4476.929734216433,
      "rating_ev": -9.245706232644807,
      "win_prob": 58.8
    },
    {
      "date": "2017-12-15",
      "country": "Vanuatu",
      "tournament": "Pacific Mini Games",
      "team1": "Vanuatu",
      "team2": "Solomon Islands",
      "original_team1": "Vanuatu",
      "original_team2": "Solomon Islands",
      "flag1": "vanuatu.png",
      "flag2": "solomon.png",
      "score1": 3,
      "score2": 2,
      "rating1": 4449.21419026774,
      "rating2": 4457.7740928715875,
      "rating_ev": 10.020638152052015,
      "win_prob": 57.8
    },
    {
      "date": "2017-12-12",
      "country": "Vanuatu",
      "tournament": "Pacific Mini Games",
      "team1": "Vanuatu",
      "team2": "Tuvalu",
      "original_team1": "Vanuatu",
      "original_team2": "Tuvalu",
      "flag1": "vanuatu.png",
      "flag2": "tuvalu.png",
      "score1": 10,
      "score2": 0,
      "rating1": 4439.193552115688,
      "rating2": 3203.9064141597178,
      "rating_ev": 41.027788251579295,
      "win_prob": 99.2
    },
    {
      "date": "2017-12-09",
      "country": "Vanuatu",
      "tournament": "Pacific Mini Games",
      "team1": "Vanuatu",
      "team2": "Fiji",
      "original_team1": "Vanuatu",
      "original_team2": "Fiji",
      "flag1": "vanuatu.png",
      "flag2": "fiji.png",
      "score1": 1,
      "score2": 1,
      "rating1": 4398.165763864109,
      "rating2": 4520.923937824622,
      "rating_ev": 1.904733588162344,
      "win_prob": 47.1
    },
    {
      "date": "2017-12-06",
      "country": "Vanuatu",
      "tournament": "Pacific Mini Games",
      "team1": "Vanuatu",
      "team2": "Tonga",
      "original_team1": "Vanuatu",
      "original_team2": "Tonga",
      "flag1": "vanuatu.png",
      "flag2": "tonga.png",
      "score1": 5,
      "score2": 0,
      "rating1": 4396.261030275947,
      "rating2": 3081.2776683023876,
      "rating_ev": -7.345228904007854,
      "win_prob": 99.5
    },
    {
      "date": "2017-12-02",
      "country": "Vanuatu",
      "tournament": "Pacific Mini Games",
      "team1": "Vanuatu",
      "team2": "New Caledonia",
      "original_team1": "Vanuatu",
      "original_team2": "New Caledonia",
      "flag1": "vanuatu.png",
      "flag2": "caledonia.png",
      "score1": 2,
      "score2": 1,
      "rating1": 4403.606259179955,
      "rating2": 4662.696818864823,
      "rating_ev": 26.778769963658306,
      "win_prob": 28.4
    },
    {
      "date": "2017-11-23",
      "country": "Vanuatu",
      "tournament": "Friendly",
      "team1": "Vanuatu",
      "team2": "Estonia",
      "original_team1": "Vanuatu",
      "original_team2": "Estonia",
      "flag1": "vanuatu.png",
      "flag2": "estonia.png",
      "score1": 0,
      "score2": 1,
      "rating1": 4376.827489216296,
      "rating2": 4972.919356643354,
      "rating_ev": 7.716477657635551,
      "win_prob": 10.5
    },
    {
      "date": "2017-07-28",
      "country": "Solomon Islands",
      "tournament": "Friendly",
      "team1": "Vanuatu",
      "team2": "Solomon Islands",
      "original_team1": "Vanuatu",
      "original_team2": "Solomon Islands",
      "flag1": "vanuatu.png",
      "flag2": "solomon.png",
      "score1": 0,
      "score2": 0,
      "rating1": 4369.111011558661,
      "rating2": 4401.822982822651,
      "rating_ev": 4.038405661410252,
      "win_prob": 35.0
    },
    {
      "date": "2016-06-04",
      "country": "Papua New Guinea",
      "tournament": "WC q and Oce Cup",
      "team1": "Vanuatu",
      "team2": "Fiji",
      "original_team1": "Vanuatu",
      "original_team2": "Fiji",
      "flag1": "vanuatu.png",
      "flag2": "fiji.png",
      "score1": 3,
      "score2": 2,
      "rating1": 4365.0726058972505,
      "rating2": 4504.449118979866,
      "rating_ev": 25.247317212443704,
      "win_prob": 30.3
    },
    {
      "date": "2016-05-31",
      "country": "Papua New Guinea",
      "tournament": "WC q and Oce Cup",
      "team1": "Vanuatu",
      "team2": "New Zealand",
      "original_team1": "Vanuatu",
      "original_team2": "New Zealand",
      "flag1": "vanuatu.png",
      "flag2": "new_zealand.png",
      "score1": 0,
      "score2": 5,
      "rating1": 4339.825288684807,
      "rating2": 4954.834947092926,
      "rating_ev": -32.99914467522103,
      "win_prob": 8.8
    },
    {
      "date": "2016-05-28",
      "country": "Papua New Guinea",
      "tournament": "WC q and Oce Cup",
      "team1": "Vanuatu",
      "team2": "Solomon Islands",
      "original_team1": "Vanuatu",
      "original_team2": "Solomon Islands",
      "flag1": "vanuatu.png",
      "flag2": "solomon.png",
      "score1": 0,
      "score2": 1,
      "rating1": 4372.824433360028,
      "rating2": 4384.20683470706,
      "rating_ev": -15.074357627097015,
      "win_prob": 52.1
    },
    {
      "date": "2016-03-26",
      "country": "Vanuatu",
      "tournament": "Friendly",
      "team1": "Vanuatu",
      "team2": "New Caledonia",
      "original_team1": "Vanuatu",
      "original_team2": "New Caledonia",
      "flag1": "vanuatu.png",
      "flag2": "caledonia.png",
      "score1": 2,
      "score2": 1,
      "rating1": 4387.898790987125,
      "rating2": 4721.15809019365,
      "rating_ev": 14.83303051349776,
      "win_prob": 24.3
    },
    {
      "date": "2015-11-10",
      "country": "Vanuatu",
      "tournament": "Friendly",
      "team1": "Vanuatu",
      "team2": "Fiji",
      "original_team1": "Vanuatu",
      "original_team2": "Fiji",
      "flag1": "vanuatu.png",
      "flag2": "fiji.png",
      "score1": 2,
      "score2": 1,
      "rating1": 4373.065760473627,
      "rating2": 4528.927105673127,
      "rating_ev": 9.351217805435226,
      "win_prob": 41.9
    },
    {
      "date": "2015-11-07",
      "country": "Vanuatu",
      "tournament": "Friendly",
      "team1": "Vanuatu",
      "team2": "Fiji",
      "original_team1": "Vanuatu",
      "original_team2": "Fiji",
      "flag1": "vanuatu.png",
      "flag2": "fiji.png",
      "score1": 1,
      "score2": 1,
      "rating1": 4363.714542668192,
      "rating2": 4538.278323478562,
      "rating_ev": 2.5235628943091797,
      "win_prob": 41.3
    },
    {
      "date": "2012-06-05",
      "country": "Solomon Islands",
      "tournament": "WC q and Oce Cup",
      "team1": "Vanuatu",
      "team2": "Tahiti",
      "original_team1": "Vanuatu",
      "original_team2": "Tahiti",
      "flag1": "vanuatu.png",
      "flag2": "tahiti.png",
      "score1": 1,
      "score2": 4,
      "rating1": 4361.190979773883,
      "rating2": 4475.3839682928065,
      "rating_ev": -38.57113156454761,
      "win_prob": 45.9
    },
    {
      "date": "2012-06-03",
      "country": "Solomon Islands",
      "tournament": "WC q and Oce Cup",
      "team1": "Vanuatu",
      "team2": "Samoa",
      "original_team1": "Vanuatu",
      "original_team2": "Samoa",
      "flag1": "vanuatu.png",
      "flag2": "samoa.png",
      "score1": 5,
      "score2": 0,
      "rating1": 4399.76211133843,
      "rating2": 3288.871004199339,
      "rating_ev": 6.97481502203118,
      "win_prob": 98.6
    },
    {
      "date": "2012-06-01",
      "country": "Solomon Islands",
      "tournament": "WC q and Oce Cup",
      "team1": "Vanuatu",
      "team2": "New Caledonia",
      "original_team1": "Vanuatu",
      "original_team2": "New Caledonia",
      "flag1": "vanuatu.png",
      "flag2": "caledonia.png",
      "score1": 2,
      "score2": 5,
      "rating1": 4392.787296316399,
      "rating2": 4630.05281788341,
      "rating_ev": -30.26554877626313,
      "win_prob": 31.5
    },
    {
      "date": "2011-09-05",
      "country": "New Caledonia",
      "tournament": "Pacific Games",
      "team1": "Vanuatu",
      "team2": "Eastern Samoa",
      "original_team1": "Vanuatu",
      "original_team2": "Eastern Samoa",
      "flag1": "vanuatu.png",
      "flag2": "us_samoa.png",
      "score1": 8,
      "score2": 0,
      "rating1": 4423.052845092662,
      "rating2": 2453.225357026388,
      "rating_ev": 10.035678042168911,
      "win_prob": 99.8
    },
    {
      "date": "2011-09-03",
      "country": "New Caledonia",
      "tournament": "Pacific Games",
      "team1": "Vanuatu",
      "team2": "Guam",
      "original_team1": "Vanuatu",
      "original_team2": "Guam",
      "flag1": "vanuatu.png",
      "flag2": "guam.png",
      "score1": 4,
      "score2": 1,
      "rating1": 4413.017167050493,
      "rating2": 3048.3803037231783,
      "rating_ev": -28.660622929774945,
      "win_prob": 99.4
    },
    {
      "date": "2011-09-01",
      "country": "New Caledonia",
      "tournament": "Pacific Games",
      "team1": "Vanuatu",
      "team2": "Solomon Islands",
      "original_team1": "Vanuatu",
      "original_team2": "Solomon Islands",
      "flag1": "vanuatu.png",
      "flag2": "solomon.png",
      "score1": 1,
      "score2": 0,
      "rating1": 4441.677789980268,
      "rating2": 4463.15638569232,
      "rating_ev": 17.302038921805433,
      "win_prob": 43.9
    },
    {
      "date": "2011-08-30",
      "country": "New Caledonia",
      "tournament": "Pacific Games",
      "team1": "Vanuatu",
      "team2": "Tuvalu",
      "original_team1": "Vanuatu",
      "original_team2": "Tuvalu",
      "flag1": "vanuatu.png",
      "flag2": "tuvalu.png",
      "score1": 5,
      "score2": 1,
      "rating1": 4424.375751058463,
      "rating2": 3232.5349433462075,
      "rating_ev": -8.914209218528413,
      "win_prob": 99.0
    },
    {
      "date": "2011-08-27",
      "country": "New Caledonia",
      "tournament": "Pacific Games",
      "team1": "Vanuatu",
      "team2": "New Caledonia",
      "original_team1": "Vanuatu",
      "original_team2": "New Caledonia",
      "flag1": "vanuatu.png",
      "flag2": "caledonia.png",
      "score1": 0,
      "score2": 5,
      "rating1": 4433.289960276991,
      "rating2": 4557.514369562204,
      "rating_ev": -58.64068081172445,
      "win_prob": 38.5
    },
    {
      "date": "2011-07-30",
      "country": "Vanuatu",
      "tournament": "Friendly",
      "team1": "Vanuatu",
      "team2": "Solomon Islands",
      "original_team1": "Vanuatu",
      "original_team2": "Solomon Islands",
      "flag1": "vanuatu.png",
      "flag2": "solomon.png",
      "score1": 2,
      "score2": 0,
      "rating1": 4491.930641088716,
      "rating2": 4498.008488748492,
      "rating_ev": 11.887181983780465,
      "win_prob": 57.6
    },
    {
      "date": "2011-07-27",
      "country": "Vanuatu",
      "tournament": "Friendly",
      "team1": "Vanuatu",
      "team2": "Solomon Islands",
      "original_team1": "Vanuatu",
      "original_team2": "Solomon Islands",
      "flag1": "vanuatu.png",
      "flag2": "solomon.png",
      "score1": 0,
      "score2": 0,
      "rating1": 4480.043459104935,
      "rating2": 4509.895670732272,
      "rating_ev": -2.051596397094727,
      "win_prob": 58.1
    },
    {
      "date": "2011-07-15",
      "country": "Fiji",
      "tournament": "Friendly",
      "team1": "Vanuatu",
      "team2": "Fiji",
      "original_team1": "Vanuatu",
      "original_team2": "Fiji",
      "flag1": "vanuatu.png",
      "flag2": "fiji.png",
      "score1": 2,
      "score2": 1,
      "rating1": 4482.09505550203,
      "rating2": 4603.348336533772,
      "rating_ev": 14.258514726686371,
      "win_prob": 25.0
    },
    {
      "date": "2011-07-13",
      "country": "Fiji",
      "tournament": "Friendly",
      "team1": "Vanuatu",
      "team2": "Fiji",
      "original_team1": "Vanuatu",
      "original_team2": "Fiji",
      "flag1": "vanuatu.png",
      "flag2": "fiji.png",
      "score1": 0,
      "score2": 2,
      "rating1": 4467.836540775344,
      "rating2": 4617.606851260459,
      "rating_ev": -6.946504599575746,
      "win_prob": 26.2
    },
    {
      "date": "2011-07-09",
      "country": "Solomon Islands",
      "tournament": "Friendly",
      "team1": "Vanuatu",
      "team2": "Solomon Islands",
      "original_team1": "Vanuatu",
      "original_team2": "Solomon Islands",
      "flag1": "vanuatu.png",
      "flag2": "solomon.png",
      "score1": 0,
      "score2": 0,
      "rating1": 4474.783045374919,
      "rating2": 4507.8440743351775,
      "rating_ev": 4.049485343933156,
      "win_prob": 35.0
    },
    {
      "date": "2011-07-07",
      "country": "Solomon Islands",
      "tournament": "Friendly",
      "team1": "Vanuatu",
      "team2": "Solomon Islands",
      "original_team1": "Vanuatu",
      "original_team2": "Solomon Islands",
      "flag1": "vanuatu.png",
      "flag2": "solomon.png",
      "score1": 1,
      "score2": 2,
      "rating1": 4470.733560030986,
      "rating2": 4511.893559679111,
      "rating_ev": -3.113123165471734,
      "win_prob": 35.6
    },
    {
      "date": "2011-01-24",
      "country": "Vanuatu",
      "tournament": "Friendly",
      "team1": "Vanuatu",
      "team2": "New Caledonia",
      "original_team1": "Vanuatu",
      "original_team2": "New Caledonia",
      "flag1": "vanuatu.png",
      "flag2": "caledonia.png",
      "score1": 0,
      "score2": 0,
      "rating1": 4473.846683196458,
      "rating2": 4515.808492390593,
      "rating_ev": -1.6671282893212265,
      "win_prob": 56.7
    },
    {
      "date": "2008-09-10",
      "country": "Vanuatu",
      "tournament": "WC q and Oce Cup",
      "team1": "Vanuatu",
      "team2": "Fiji",
      "original_team1": "Vanuatu",
      "original_team2": "Fiji",
      "flag1": "vanuatu.png",
      "flag2": "fiji.png",
      "score1": 2,
      "score2": 1,
      "rating1": 4475.513811485779,
      "rating2": 4563.609813699778,
      "rating_ev": 15.402744298738071,
      "win_prob": 47.9
    },
    {
      "date": "2008-09-06",
      "country": "Fiji",
      "tournament": "WC q and Oce Cup",
      "team1": "Vanuatu",
      "team2": "Fiji",
      "original_team1": "Vanuatu",
      "original_team2": "Fiji",
      "flag1": "vanuatu.png",
      "flag2": "fiji.png",
      "score1": 0,
      "score2": 2,
      "rating1": 4460.111067187041,
      "rating2": 4579.012557998516,
      "rating_ev": -16.91450420502224,
      "win_prob": 30.7
    },
    {
      "date": "2008-07-07",
      "country": "Solomon Islands",
      "tournament": "Friendly tournament",
      "team1": "Vanuatu",
      "team2": "Solomon Islands",
      "original_team1": "Vanuatu",
      "original_team2": "Solomon Islands",
      "flag1": "vanuatu.png",
      "flag2": "solomon.png",
      "score1": 2,
      "score2": 1,
      "rating1": 4477.025571392063,
      "rating2": 4508.780436513639,
      "rating_ev": 24.402689346666193,
      "win_prob": 31.1
    },
    {
      "date": "2008-06-21",
      "country": "New Caledonia",
      "tournament": "WC q and Oce Cup",
      "team1": "Vanuatu",
      "team2": "New Caledonia",
      "original_team1": "Vanuatu",
      "original_team2": "New Caledonia",
      "flag1": "vanuatu.png",
      "flag2": "caledonia.png",
      "score1": 0,
      "score2": 3,
      "rating1": 4452.622882045397,
      "rating2": 4600.91024092343,
      "rating_ev": -29.857190194903524,
      "win_prob": 30.4
    },
    {
      "date": "2008-06-14",
      "country": "Vanuatu",
      "tournament": "WC q and Oce Cup",
      "team1": "Vanuatu",
      "team2": "New Caledonia",
      "original_team1": "Vanuatu",
      "original_team2": "New Caledonia",
      "flag1": "vanuatu.png",
      "flag2": "caledonia.png",
      "score1": 1,
      "score2": 1,
      "rating1": 4482.480072240301,
      "rating2": 4571.053050728527,
      "rating_ev": -0.4035535993753001,
      "win_prob": 51.3
    },
    {
      "date": "2007-11-21",
      "country": "New Zealand",
      "tournament": "WC q and Oce Cup",
      "team1": "Vanuatu",
      "team2": "New Zealand",
      "original_team1": "Vanuatu",
      "original_team2": "New Zealand",
      "flag1": "vanuatu.png",
      "flag2": "new_zealand.png",
      "score1": 1,
      "score2": 4,
      "rating1": 4482.883625839676,
      "rating2": 4968.107841499234,
      "rating_ev": -7.783346555533171,
      "win_prob": 7.9
    },
    {
      "date": "2007-11-17",
      "country": "Vanuatu",
      "tournament": "WC q and Oce Cup",
      "team1": "Vanuatu",
      "team2": "New Zealand",
      "original_team1": "Vanuatu",
      "original_team2": "New Zealand",
      "flag1": "vanuatu.png",
      "flag2": "new_zealand.png",
      "score1": 1,
      "score2": 2,
      "rating1": 4490.666972395209,
      "rating2": 4960.324494943701,
      "rating_ev": 8.729203476837938,
      "win_prob": 16.1
    },
    {
      "date": "2007-09-07",
      "country": "Samoa",
      "tournament": "W Cup and Oce Cup q and S Pac G",
      "team1": "Vanuatu",
      "team2": "Solomon Islands",
      "original_team1": "Vanuatu",
      "original_team2": "Solomon Islands",
      "flag1": "vanuatu.png",
      "flag2": "solomon.png",
      "score1": 2,
      "score2": 0,
      "rating1": 4481.937768918371,
      "rating2": 4533.183125860305,
      "rating_ev": 34.84349380327785,
      "win_prob": 37.0
    },
    {
      "date": "2007-09-05",
      "country": "Samoa",
      "tournament": "W Cup and Oce Cup q and S Pac G",
      "team1": "Vanuatu",
      "team2": "Fiji",
      "original_team1": "Vanuatu",
      "original_team2": "Fiji",
      "flag1": "vanuatu.png",
      "flag2": "fiji.png",
      "score1": 0,
      "score2": 3,
      "rating1": 4447.094275115093,
      "rating2": 4668.7381089361625,
      "rating_ev": -31.313536151413246,
      "win_prob": 33.2
    },
    {
      "date": "2007-09-03",
      "country": "Samoa",
      "tournament": "W Cup and Oce Cup q and S Pac G",
      "team1": "Vanuatu",
      "team2": "Tonga",
      "original_team1": "Vanuatu",
      "original_team2": "Tonga",
      "flag1": "vanuatu.png",
      "flag2": "tonga.png",
      "score1": 4,
      "score2": 1,
      "rating1": 4478.4078112665065,
      "rating2": 3279.006455988713,
      "rating_ev": -22.613758594713545,
      "win_prob": 99.1
    },
    {
      "date": "2007-09-01",
      "country": "Samoa",
      "tournament": "W Cup and Oce Cup q and S Pac G",
      "team1": "Vanuatu",
      "team2": "Solomon Islands",
      "original_team1": "Vanuatu",
      "original_team2": "Solomon Islands",
      "flag1": "vanuatu.png",
      "flag2": "solomon.png",
      "score1": 0,
      "score2": 2,
      "rating1": 4501.02156986122,
      "rating2": 4606.025788723439,
      "rating_ev": -24.260076902239234,
      "win_prob": 43.8
    },
    {
      "date": "2007-08-29",
      "country": "Samoa",
      "tournament": "W Cup and Oce Cup q and S Pac G",
      "team1": "Vanuatu",
      "team2": "Eastern Samoa",
      "original_team1": "Vanuatu",
      "original_team2": "Eastern Samoa",
      "flag1": "vanuatu.png",
      "flag2": "us_samoa.png",
      "score1": 15,
      "score2": 0,
      "rating1": 4525.281646763459,
      "rating2": 2445.3510282727725,
      "rating_ev": 15.17839074182666,
      "win_prob": 99.8
    },
    {
      "date": "2007-08-25",
      "country": "Samoa",
      "tournament": "W Cup and Oce Cup q and S Pac G",
      "team1": "Vanuatu",
      "team2": "Samoa",
      "original_team1": "Vanuatu",
      "original_team2": "Samoa",
      "flag1": "vanuatu.png",
      "flag2": "samoa.png",
      "score1": 4,
      "score2": 0,
      "rating1": 4510.103256021633,
      "rating2": 3352.63950771305,
      "rating_ev": -1.3928502683916122,
      "win_prob": 98.2
    },
    {
      "date": "2007-07-19",
      "country": "New Caledonia",
      "tournament": "Friendly",
      "team1": "Vanuatu",
      "team2": "New Caledonia",
      "original_team1": "Vanuatu",
      "original_team2": "New Caledonia",
      "flag1": "vanuatu.png",
      "flag2": "caledonia.png",
      "score1": 2,
      "score2": 0,
      "rating1": 4511.496106290024,
      "rating2": 4517.0280870282295,
      "rating_ev": 17.869042893472397,
      "win_prob": 35.0
    },
    {
      "date": "2007-07-17",
      "country": "New Caledonia",
      "tournament": "Friendly",
      "team1": "Vanuatu",
      "team2": "New Caledonia",
      "original_team1": "Vanuatu",
      "original_team2": "New Caledonia",
      "flag1": "vanuatu.png",
      "flag2": "caledonia.png",
      "score1": 3,
      "score2": 5,
      "rating1": 4493.627063396551,
      "rating2": 4534.897129921702,
      "rating_ev": -10.383479270009957,
      "win_prob": 37.1
    },
    {
      "date": "2004-06-06",
      "country": "Australia",
      "tournament": "WC q and Oce Cup",
      "team1": "Vanuatu",
      "team2": "Tahiti",
      "original_team1": "Vanuatu",
      "original_team2": "Tahiti",
      "flag1": "vanuatu.png",
      "flag2": "tahiti.png",
      "score1": 1,
      "score2": 2,
      "rating1": 4504.010542666561,
      "rating2": 4361.215403500875,
      "rating_ev": -25.475888869495975,
      "win_prob": 70.1
    },
    {
      "date": "2004-06-04",
      "country": "Australia",
      "tournament": "WC q and Oce Cup",
      "team1": "Vanuatu",
      "team2": "Australia",
      "original_team1": "Vanuatu",
      "original_team2": "Australia",
      "flag1": "vanuatu.png",
      "flag2": "australia.png",
      "score1": 0,
      "score2": 3,
      "rating1": 4529.486431536057,
      "rating2": 5404.555463773486,
      "rating_ev": 14.26025149981524,
      "win_prob": 1.7
    },
    {
      "date": "2004-06-02",
      "country": "Australia",
      "tournament": "WC q and Oce Cup",
      "team1": "Vanuatu",
      "team2": "New Zealand",
      "original_team1": "Vanuatu",
      "original_team2": "New Zealand",
      "flag1": "vanuatu.png",
      "flag2": "new_zealand.png",
      "score1": 4,
      "score2": 2,
      "rating1": 4515.226180036242,
      "rating2": 4991.999990986626,
      "rating_ev": 62.10409238150896,
      "win_prob": 7.3
    },
    {
      "date": "2004-05-31",
      "country": "Australia",
      "tournament": "WC q and Oce Cup",
      "team1": "Vanuatu",
      "team2": "Fiji",
      "original_team1": "Vanuatu",
      "original_team2": "Fiji",
      "flag1": "vanuatu.png",
      "flag2": "fiji.png",
      "score1": 0,
      "score2": 1,
      "rating1": 4453.122087654733,
      "rating2": 4632.8767016133725,
      "rating_ev": -3.693380524105123,
      "win_prob": 31.9
    },
    {
      "date": "2004-05-29",
      "country": "Australia",
      "tournament": "WC q and Oce Cup",
      "team1": "Vanuatu",
      "team2": "Solomon Islands",
      "original_team1": "Vanuatu",
      "original_team2": "Solomon Islands",
      "flag1": "vanuatu.png",
      "flag2": "solomon.png",
      "score1": 0,
      "score2": 1,
      "rating1": 4456.815468178838,
      "rating2": 4545.746423177053,
      "rating_ev": -9.816780361175915,
      "win_prob": 42.4
    },
    {
      "date": "2004-05-19",
      "country": "Samoa",
      "tournament": "WC and Oce Cup q",
      "team1": "Vanuatu",
      "team2": "Fiji",
      "original_team1": "Vanuatu",
      "original_team2": "Fiji",
      "flag1": "vanuatu.png",
      "flag2": "fiji.png",
      "score1": 3,
      "score2": 0,
      "rating1": 4466.632248540014,
      "rating2": 4638.098152735121,
      "rating_ev": 57.76453297906028,
      "win_prob": 22.2
    },
    {
      "date": "2004-05-15",
      "country": "Samoa",
      "tournament": "WC and Oce Cup q",
      "team1": "Vanuatu",
      "team2": "Samoa",
      "original_team1": "Vanuatu",
      "original_team2": "Samoa",
      "flag1": "vanuatu.png",
      "flag2": "samoa.png",
      "score1": 3,
      "score2": 0,
      "rating1": 4408.867715560954,
      "rating2": 3341.1533235729785,
      "rating_ev": -11.004268908742233,
      "win_prob": 97.8
    },
    {
      "date": "2004-05-12",
      "country": "Samoa",
      "tournament": "WC and Oce Cup q",
      "team1": "Vanuatu",
      "team2": "Eastern Samoa",
      "original_team1": "Vanuatu",
      "original_team2": "Eastern Samoa",
      "flag1": "vanuatu.png",
      "flag2": "us_samoa.png",
      "score1": 9,
      "score2": 1,
      "rating1": 4419.871984469696,
      "rating2": 2543.876792302762,
      "rating_ev": 12.076626501495412,
      "win_prob": 99.7
    },
    {
      "date": "2004-05-10",
      "country": "Samoa",
      "tournament": "WC and Oce Cup q",
      "team1": "Vanuatu",
      "team2": "Papua New Guinea",
      "original_team1": "Vanuatu",
      "original_team2": "Papua New Guinea",
      "flag1": "vanuatu.png",
      "flag2": "papua.png",
      "score1": 1,
      "score2": 1,
      "rating1": 4407.795357968201,
      "rating2": 4194.039011270886,
      "rating_ev": -14.388687563154235,
      "win_prob": 74.3
    },
    {
      "date": "2004-04-06",
      "country": "Vanuatu",
      "tournament": "Friendly",
      "team1": "Vanuatu",
      "team2": "Solomon Islands",
      "original_team1": "Vanuatu",
      "original_team2": "Solomon Islands",
      "flag1": "vanuatu.png",
      "flag2": "solomon.png",
      "score1": 1,
      "score2": 2,
      "rating1": 4422.184045531355,
      "rating2": 4529.744132190918,
      "rating_ev": -7.0063670486197225,
      "win_prob": 50.7
    },
    {
      "date": "2004-04-03",
      "country": "Vanuatu",
      "tournament": "Friendly",
      "team1": "Vanuatu",
      "team2": "Solomon Islands",
      "original_team1": "Vanuatu",
      "original_team2": "Solomon Islands",
      "flag1": "vanuatu.png",
      "flag2": "solomon.png",
      "score1": 1,
      "score2": 2,
      "rating1": 4429.190412579975,
      "rating2": 4522.7377651422985,
      "rating_ev": -7.450215016546281,
      "win_prob": 52.3
    },
    {
      "date": "2003-07-11",
      "country": "Fiji",
      "tournament": "South Pacific Games",
      "team1": "Vanuatu",
      "team2": "Tahiti",
      "original_team1": "Vanuatu",
      "original_team2": "Tahiti",
      "flag1": "vanuatu.png",
      "flag2": "tahiti.png",
      "score1": 1,
      "score2": 0,
      "rating1": 4436.640627596521,
      "rating2": 4559.426075316468,
      "rating_ev": 24.136207048944925,
      "win_prob": 32.1
    },
    {
      "date": "2003-07-09",
      "country": "Fiji",
      "tournament": "South Pacific Games",
      "team1": "Vanuatu",
      "team2": "New Caledonia",
      "original_team1": "Vanuatu",
      "original_team2": "New Caledonia",
      "flag1": "vanuatu.png",
      "flag2": "caledonia.png",
      "score1": 1,
      "score2": 1,
      "rating1": 4412.504420547576,
      "rating2": 4494.175079709237,
      "rating_ev": 5.53360659826285,
      "win_prob": 39.9
    },
    {
      "date": "2003-07-07",
      "country": "Fiji",
      "tournament": "South Pacific Games",
      "team1": "Vanuatu",
      "team2": "Kiribati",
      "original_team1": "Vanuatu",
      "original_team2": "Kiribati",
      "flag1": "vanuatu.png",
      "flag2": "kiribati.png",
      "score1": 18,
      "score2": 0,
      "rating1": 4406.970813949313,
      "rating2": 2424.0872523371236,
      "rating_ev": 17.09153409402097,
      "win_prob": 99.8
    },
    {
      "date": "2003-07-03",
      "country": "Fiji",
      "tournament": "South Pacific Games",
      "team1": "Vanuatu",
      "team2": "Tuvalu",
      "original_team1": "Vanuatu",
      "original_team2": "Tuvalu",
      "flag1": "vanuatu.png",
      "flag2": "tuvalu.png",
      "score1": 1,
      "score2": 0,
      "rating1": 4389.879279855292,
      "rating2": 3124.0703990136362,
      "rating_ev": -53.925442828144696,
      "win_prob": 99.3
    },
    {
      "date": "2003-07-01",
      "country": "Fiji",
      "tournament": "South Pacific Games",
      "team1": "Vanuatu",
      "team2": "Solomon Islands",
      "original_team1": "Vanuatu",
      "original_team2": "Solomon Islands",
      "flag1": "vanuatu.png",
      "flag2": "solomon.png",
      "score1": 2,
      "score2": 2,
      "rating1": 4443.804722683437,
      "rating2": 4529.953170359496,
      "rating_ev": 5.8362604143694625,
      "win_prob": 39.4
    },
    {
      "date": "2003-06-30",
      "country": "Fiji",
      "tournament": "South Pacific Games",
      "team1": "Vanuatu",
      "team2": "Fiji",
      "original_team1": "Vanuatu",
      "original_team2": "Fiji",
      "flag1": "vanuatu.png",
      "flag2": "fiji.png",
      "score1": 0,
      "score2": 0,
      "rating1": 4437.9684622690675,
      "rating2": 4688.375278012448,
      "rating_ev": 23.189700249572525,
      "win_prob": 15.0
    },
    {
      "date": "2002-07-14",
      "country": "New Zealand",
      "tournament": "Oceania Nations Cup",
      "team1": "Vanuatu",
      "team2": "Tahiti",
      "original_team1": "Vanuatu",
      "original_team2": "Tahiti",
      "flag1": "vanuatu.png",
      "flag2": "tahiti.png",
      "score1": 0,
      "score2": 1,
      "rating1": 4414.778762019495,
      "rating2": 4655.324482761705,
      "rating_ev": 0.3610708926935331,
      "win_prob": 25.8
    },
    {
      "date": "2002-07-12",
      "country": "New Zealand",
      "tournament": "Oceania Nations Cup",
      "team1": "Vanuatu",
      "team2": "New Zealand",
      "original_team1": "Vanuatu",
      "original_team2": "New Zealand",
      "flag1": "vanuatu.png",
      "flag2": "new_zealand.png",
      "score1": 0,
      "score2": 3,
      "rating1": 4414.417691126801,
      "rating2": 5112.80565622432,
      "rating_ev": 4.864540515622139,
      "win_prob": 3.3
    },
    {
      "date": "2002-07-10",
      "country": "New Zealand",
      "tournament": "Oceania Nations Cup",
      "team1": "Vanuatu",
      "team2": "New Caledonia",
      "original_team1": "Vanuatu",
      "original_team2": "New Caledonia",
      "flag1": "vanuatu.png",
      "flag2": "caledonia.png",
      "score1": 1,
      "score2": 0,
      "rating1": 4409.553150611179,
      "rating2": 4424.490533288602,
      "rating_ev": 16.858817572294356,
      "win_prob": 44.7
    },
    {
      "date": "2002-07-08",
      "country": "New Zealand",
      "tournament": "Oceania Nations Cup",
      "team1": "Vanuatu",
      "team2": "Fiji",
      "original_team1": "Vanuatu",
      "original_team2": "Fiji",
      "flag1": "vanuatu.png",
      "flag2": "fiji.png",
      "score1": 1,
      "score2": 0,
      "rating1": 4392.694333038885,
      "rating2": 4758.649720460521,
      "rating_ev": 39.994526536862395,
      "win_prob": 12.8
    },
    {
      "date": "2002-07-06",
      "country": "New Zealand",
      "tournament": "Oceania Nations Cup",
      "team1": "Vanuatu",
      "team2": "Australia",
      "original_team1": "Vanuatu",
      "original_team2": "Australia",
      "flag1": "vanuatu.png",
      "flag2": "australia.png",
      "score1": 0,
      "score2": 2,
      "rating1": 4352.6998065020225,
      "rating2": 5341.356554276495,
      "rating_ev": 27.93279430280836,
      "win_prob": 1.6
    },
    {
      "date": "2001-06-13",
      "country": "New Zealand",
      "tournament": "World Cup qualifier",
      "team1": "Vanuatu",
      "team2": "New Zealand",
      "original_team1": "Vanuatu",
      "original_team2": "New Zealand",
      "flag1": "vanuatu.png",
      "flag2": "new_zealand.png",
      "score1": 0,
      "score2": 7,
      "rating1": 4324.767012199214,
      "rating2": 5040.754651487973,
      "rating_ev": -42.972197998606134,
      "win_prob": 4.3
    },
    {
      "date": "2001-06-08",
      "country": "New Zealand",
      "tournament": "World Cup qualifier",
      "team1": "Vanuatu",
      "team2": "Solomon Islands",
      "original_team1": "Vanuatu",
      "original_team2": "Solomon Islands",
      "flag1": "vanuatu.png",
      "flag2": "solomon.png",
      "score1": 2,
      "score2": 7,
      "rating1": 4367.73921019782,
      "rating2": 4637.99956226376,
      "rating_ev": -55.173033645641226,
      "win_prob": 33.1
    },
    {
      "date": "2001-06-06",
      "country": "New Zealand",
      "tournament": "World Cup qualifier",
      "team1": "Vanuatu",
      "team2": "Cook Islands",
      "original_team1": "Vanuatu",
      "original_team2": "Cook Islands",
      "flag1": "vanuatu.png",
      "flag2": "cook.png",
      "score1": 8,
      "score2": 1,
      "rating1": 4422.9122438434615,
      "rating2": 3098.4422198883863,
      "rating_ev": 19.766680041931977,
      "win_prob": 99.2
    },
    {
      "date": "2001-06-04",
      "country": "New Zealand",
      "tournament": "World Cup qualifier",
      "team1": "Vanuatu",
      "team2": "Tahiti",
      "original_team1": "Vanuatu",
      "original_team2": "Tahiti",
      "flag1": "vanuatu.png",
      "flag2": "tahiti.png",
      "score1": 1,
      "score2": 6,
      "rating1": 4403.1455638015295,
      "rating2": 4632.818006472739,
      "rating_ev": -57.90581686960104,
      "win_prob": 37.7
    },
    {
      "date": "2000-06-28",
      "country": "Tahiti",
      "tournament": "Oceania Nations Cup",
      "team1": "Vanuatu",
      "team2": "Solomon Islands",
      "original_team1": "Vanuatu",
      "original_team2": "Solomon Islands",
      "flag1": "vanuatu.png",
      "flag2": "solomon.png",
      "score1": 1,
      "score2": 2,
      "rating1": 4461.051380671131,
      "rating2": 4559.156705409722,
      "rating_ev": -9.195827158618158,
      "win_prob": 41.3
    },
    {
      "date": "2000-06-25",
      "country": "Tahiti",
      "tournament": "Oceania Nations Cup",
      "team1": "Vanuatu",
      "team2": "Australia",
      "original_team1": "Vanuatu",
      "original_team2": "Australia",
      "flag1": "vanuatu.png",
      "flag2": "australia.png",
      "score1": 0,
      "score2": 1,
      "rating1": 4470.247207829749,
      "rating2": 5298.578789890147,
      "rating_ev": 35.23048112639208,
      "win_prob": 2.6
    },
    {
      "date": "2000-06-23",
      "country": "Tahiti",
      "tournament": "Oceania Nations Cup",
      "team1": "Vanuatu",
      "team2": "Tahiti",
      "original_team1": "Vanuatu",
      "original_team2": "Tahiti",
      "flag1": "vanuatu.png",
      "flag2": "tahiti.png",
      "score1": 3,
      "score2": 2,
      "rating1": 4435.016726703357,
      "rating2": 4574.912189603138,
      "rating_ev": 31.676793300812278,
      "win_prob": 20.9
    },
    {
      "date": "2000-06-21",
      "country": "Tahiti",
      "tournament": "Oceania Nations Cup",
      "team1": "Vanuatu",
      "team2": "New Zealand",
      "original_team1": "Vanuatu",
      "original_team2": "New Zealand",
      "flag1": "vanuatu.png",
      "flag2": "new_zealand.png",
      "score1": 1,
      "score2": 3,
      "rating1": 4403.339933402544,
      "rating2": 5048.020347875155,
      "rating_ev": 10.179797583094114,
      "win_prob": 5.8
    },
    {
      "date": "2000-06-15",
      "country": "New Caledonia",
      "tournament": "Friendly",
      "team1": "Vanuatu",
      "team2": "New Caledonia",
      "original_team1": "Vanuatu",
      "original_team2": "New Caledonia",
      "flag1": "vanuatu.png",
      "flag2": "caledonia.png",
      "score1": 0,
      "score2": 1,
      "rating1": 4393.16013581945,
      "rating2": 4479.104434172745,
      "rating_ev": -1.6926185788015573,
      "win_prob": 31.0
    },
    {
      "date": "2000-06-12",
      "country": "New Caledonia",
      "tournament": "Friendly",
      "team1": "Vanuatu",
      "team2": "New Caledonia",
      "original_team1": "Vanuatu",
      "original_team2": "New Caledonia",
      "flag1": "vanuatu.png",
      "flag2": "caledonia.png",
      "score1": 1,
      "score2": 3,
      "rating1": 4394.852754398252,
      "rating2": 4477.411815593943,
      "rating_ev": -9.073033657764427,
      "win_prob": 32.7
    },
    {
      "date": "2000-04-15",
      "country": "Fiji",
      "tournament": "Oce Cup q & Melanesian Cup",
      "team1": "Vanuatu",
      "team2": "Papua New Guinea",
      "original_team1": "Vanuatu",
      "original_team2": "Papua New Guinea",
      "flag1": "vanuatu.png",
      "flag2": "papua.png",
      "score1": 4,
      "score2": 1,
      "rating1": 4403.925788056016,
      "rating2": 4260.675318654057,
      "rating_ev": 36.60240963486831,
      "win_prob": 57.6
    },
    {
      "date": "2000-04-13",
      "country": "Fiji",
      "tournament": "Oce Cup q & Melanesian Cup",
      "team1": "Vanuatu",
      "team2": "New Caledonia",
      "original_team1": "Vanuatu",
      "original_team2": "New Caledonia",
      "flag1": "vanuatu.png",
      "flag2": "caledonia.png",
      "score1": 6,
      "score2": 0,
      "rating1": 4367.323378421148,
      "rating2": 4468.338781936179,
      "rating_ev": 92.05968783024491,
      "win_prob": 22.4
    },
    {
      "date": "2000-04-11",
      "country": "Fiji",
      "tournament": "Oce Cup q & Melanesian Cup",
      "team1": "Vanuatu",
      "team2": "Fiji",
      "original_team1": "Vanuatu",
      "original_team2": "Fiji",
      "flag1": "vanuatu.png",
      "flag2": "fiji.png",
      "score1": 1,
      "score2": 4,
      "rating1": 4275.263690590903,
      "rating2": 4782.851370797674,
      "rating_ev": -6.39658283845074,
      "win_prob": 7.2
    },
    {
      "date": "2000-04-10",
      "country": "Fiji",
      "tournament": "Oce Cup q & Melanesian Cup",
      "team1": "Vanuatu",
      "team2": "Solomon Islands",
      "original_team1": "Vanuatu",
      "original_team2": "Solomon Islands",
      "flag1": "vanuatu.png",
      "flag2": "solomon.png",
      "score1": 1,
      "score2": 2,
      "rating1": 4281.660273429354,
      "rating2": 4571.822997417124,
      "rating_ev": 3.6323017787744902,
      "win_prob": 21.5
    },
    {
      "date": "1998-09-30",
      "country": "Australia",
      "tournament": "Oceania Nations Cup",
      "team1": "Vanuatu",
      "team2": "Tahiti",
      "original_team1": "Vanuatu",
      "original_team2": "Tahiti",
      "flag1": "vanuatu.png",
      "flag2": "tahiti.png",
      "score1": 1,
      "score2": 5,
      "rating1": 4278.027971650579,
      "rating2": 4727.236739794209,
      "rating_ev": -30.38781530598044,
      "win_prob": 15.7
    },
    {
      "date": "1998-09-28",
      "country": "Australia",
      "tournament": "Oceania Nations Cup",
      "team1": "Vanuatu",
      "team2": "New Zealand",
      "original_team1": "Vanuatu",
      "original_team2": "New Zealand",
      "flag1": "vanuatu.png",
      "flag2": "new_zealand.png",
      "score1": 1,
      "score2": 8,
      "rating1": 4308.41578695656,
      "rating2": 5025.1700842643695,
      "rating_ev": -49.2280615402542,
      "win_prob": 6.9
    },
    {
      "date": "1998-09-12",
      "country": "Vanuatu",
      "tournament": "Oce Cup q & Melanesian Cup",
      "team1": "Vanuatu",
      "team2": "New Caledonia",
      "original_team1": "Vanuatu",
      "original_team2": "New Caledonia",
      "flag1": "vanuatu.png",
      "flag2": "caledonia.png",
      "score1": 3,
      "score2": 2,
      "rating1": 4357.643848496814,
      "rating2": 4458.271872455795,
      "rating_ev": 16.247522968300473,
      "win_prob": 46.3
    },
    {
      "date": "1998-09-10",
      "country": "Vanuatu",
      "tournament": "Oce Cup q & Melanesian Cup",
      "team1": "Vanuatu",
      "team2": "Solomon Islands",
      "original_team1": "Vanuatu",
      "original_team2": "Solomon Islands",
      "flag1": "vanuatu.png",
      "flag2": "solomon.png",
      "score1": 3,
      "score2": 1,
      "rating1": 4341.396325528513,
      "rating2": 4605.805321094884,
      "rating_ev": 42.581543220857384,
      "win_prob": 25.4
    },
    {
      "date": "1998-09-08",
      "country": "Vanuatu",
      "tournament": "Oce Cup q & Melanesian Cup",
      "team1": "Vanuatu",
      "team2": "Papua New Guinea",
      "original_team1": "Vanuatu",
      "original_team2": "Papua New Guinea",
      "flag1": "vanuatu.png",
      "flag2": "papua.png",
      "score1": 1,
      "score2": 1,
      "rating1": 4298.814782307656,
      "rating2": 4410.703442759101,
      "rating_ev": 1.1716254401044353,
      "win_prob": 48.4
    },
    {
      "date": "1998-09-07",
      "country": "Vanuatu",
      "tournament": "Oce Cup q & Melanesian Cup",
      "team1": "Vanuatu",
      "team2": "Fiji",
      "original_team1": "Vanuatu",
      "original_team2": "Fiji",
      "flag1": "vanuatu.png",
      "flag2": "fiji.png",
      "score1": 1,
      "score2": 2,
      "rating1": 4297.643156867552,
      "rating2": 4741.888965696853,
      "rating_ev": 7.148054457853505,
      "win_prob": 17.7
    },
    {
      "date": "1996-09-20",
      "country": "Papua New Guinea",
      "tournament": "World Cup qualifier",
      "team1": "Vanuatu",
      "team2": "Papua New Guinea",
      "original_team1": "Vanuatu",
      "original_team2": "Papua New Guinea",
      "flag1": "vanuatu.png",
      "flag2": "papua.png",
      "score1": 1,
      "score2": 2,
      "rating1": 4290.495102409698,
      "rating2": 4420.540523721048,
      "rating_ev": -0.6356898866888514,
      "win_prob": 26.8
    },
    {
      "date": "1996-09-18",
      "country": "Papua New Guinea",
      "tournament": "World Cup qualifier",
      "team1": "Vanuatu",
      "team2": "Solomon Islands",
      "original_team1": "Vanuatu",
      "original_team2": "Solomon Islands",
      "flag1": "vanuatu.png",
      "flag2": "solomon.png",
      "score1": 1,
      "score2": 1,
      "rating1": 4291.130792296387,
      "rating2": 4611.933686748232,
      "rating_ev": 21.391242862226136,
      "win_prob": 17.1
    },
    {
      "date": "1995-08-26",
      "country": "Tahiti",
      "tournament": "South Pacific Games",
      "team1": "Vanuatu",
      "team2": "Fiji",
      "original_team1": "Vanuatu",
      "original_team2": "Fiji",
      "flag1": "vanuatu.png",
      "flag2": "fiji.png",
      "score1": 0,
      "score2": 3,
      "rating1": 4269.739549434161,
      "rating2": 4735.1420073661475,
      "rating_ev": -15.37377944502623,
      "win_prob": 13.3
    },
    {
      "date": "1995-08-24",
      "country": "Tahiti",
      "tournament": "South Pacific Games",
      "team1": "Vanuatu",
      "team2": "Tahiti",
      "original_team1": "Vanuatu",
      "original_team2": "Tahiti",
      "flag1": "vanuatu.png",
      "flag2": "tahiti.png",
      "score1": 0,
      "score2": 3,
      "rating1": 4285.113328879187,
      "rating2": 4845.858566306329,
      "rating_ev": -3.1531902765364066,
      "win_prob": 5.7
    },
    {
      "date": "1995-08-22",
      "country": "Tahiti",
      "tournament": "South Pacific Games",
      "team1": "Vanuatu",
      "team2": "Fiji",
      "original_team1": "Vanuatu",
      "original_team2": "Fiji",
      "flag1": "vanuatu.png",
      "flag2": "fiji.png",
      "score1": 1,
      "score2": 3,
      "rating1": 4288.2665191557235,
      "rating2": 4724.253431009217,
      "rating_ev": -2.4189469064585865,
      "win_prob": 13.5
    },
    {
      "date": "1995-08-20",
      "country": "Tahiti",
      "tournament": "South Pacific Games",
      "team1": "Vanuatu",
      "team2": "Papua New Guinea",
      "original_team1": "Vanuatu",
      "original_team2": "Papua New Guinea",
      "flag1": "vanuatu.png",
      "flag2": "papua.png",
      "score1": 3,
      "score2": 0,
      "rating1": 4290.685466062182,
      "rating2": 4375.457827997814,
      "rating_ev": 52.014446821119236,
      "win_prob": 30.4
    },
    {
      "date": "1995-08-16",
      "country": "Tahiti",
      "tournament": "South Pacific Games",
      "team1": "Vanuatu",
      "team2": "Guam",
      "original_team1": "Vanuatu",
      "original_team2": "Guam",
      "flag1": "vanuatu.png",
      "flag2": "guam.png",
      "score1": 6,
      "score2": 0,
      "rating1": 4238.671019241063,
      "rating2": 3146.6970135634942,
      "rating_ev": 19.247955074818492,
      "win_prob": 98.4
    },
    {
      "date": "1994-07-08",
      "country": "Solomon Islands",
      "tournament": "Oce Cup q & Melanesian Cup",
      "team1": "Vanuatu",
      "team2": "Fiji",
      "original_team1": "Vanuatu",
      "original_team2": "Fiji",
      "flag1": "vanuatu.png",
      "flag2": "fiji.png",
      "score1": 2,
      "score2": 4,
      "rating1": 4219.423064166244,
      "rating2": 4741.457544422613,
      "rating_ev": 2.9209932262356233,
      "win_prob": 9.5
    },
    {
      "date": "1994-07-07",
      "country": "Solomon Islands",
      "tournament": "Oce Cup q & Melanesian Cup",
      "team1": "Vanuatu",
      "team2": "Papua New Guinea",
      "original_team1": "Vanuatu",
      "original_team2": "Papua New Guinea",
      "flag1": "vanuatu.png",
      "flag2": "papua.png",
      "score1": 1,
      "score2": 1,
      "rating1": 4216.502070940009,
      "rating2": 4409.061439721594,
      "rating_ev": 12.980479901809304,
      "win_prob": 27.7
    },
    {
      "date": "1994-07-06",
      "country": "Solomon Islands",
      "tournament": "Oce Cup q & Melanesian Cup",
      "team1": "Vanuatu",
      "team2": "Solomon Islands",
      "original_team1": "Vanuatu",
      "original_team2": "Solomon Islands",
      "flag1": "vanuatu.png",
      "flag2": "solomon.png",
      "score1": 0,
      "score2": 4,
      "rating1": 4203.521591038199,
      "rating2": 4575.039434202878,
      "rating_ev": -29.039939533753568,
      "win_prob": 14.1
    },
    {
      "date": "1994-07-05",
      "country": "Solomon Islands",
      "tournament": "Oce Cup q & Melanesian Cup",
      "team1": "Vanuatu",
      "team2": "New Caledonia",
      "original_team1": "Vanuatu",
      "original_team2": "New Caledonia",
      "flag1": "vanuatu.png",
      "flag2": "caledonia.png",
      "score1": 2,
      "score2": 3,
      "rating1": 4232.561530571953,
      "rating2": 4585.4545347996045,
      "rating_ev": 7.707072630074435,
      "win_prob": 16.8
    },
    {
      "date": "1993-12-16",
      "country": "Vanuatu",
      "tournament": "South Pacific Mini Games",
      "team1": "Vanuatu",
      "team2": "New Caledonia",
      "original_team1": "Vanuatu",
      "original_team2": "New Caledonia",
      "flag1": "vanuatu.png",
      "flag2": "caledonia.png",
      "score1": 1,
      "score2": 2,
      "rating1": 4224.8544579418785,
      "rating2": 4640.550553845245,
      "rating_ev": 5.35280288476406,
      "win_prob": 19.8
    },
    {
      "date": "1993-12-14",
      "country": "Vanuatu",
      "tournament": "South Pacific Mini Games",
      "team1": "Vanuatu",
      "team2": "Fiji",
      "original_team1": "Vanuatu",
      "original_team2": "Fiji",
      "flag1": "vanuatu.png",
      "flag2": "fiji.png",
      "score1": 0,
      "score2": 2,
      "rating1": 4219.5016550571145,
      "rating2": 4764.821806930037,
      "rating_ev": -1.9904858666695873,
      "win_prob": 13.4
    },
    {
      "date": "1993-12-13",
      "country": "Vanuatu",
      "tournament": "South Pacific Mini Games",
      "team1": "Vanuatu",
      "team2": "Papua New Guinea",
      "original_team1": "Vanuatu",
      "original_team2": "Papua New Guinea",
      "flag1": "vanuatu.png",
      "flag2": "papua.png",
      "score1": 1,
      "score2": 0,
      "rating1": 4221.492140923784,
      "rating2": 4403.099429890571,
      "rating_ev": 21.670440268074344,
      "win_prob": 36.7
    },
    {
      "date": "1993-12-10",
      "country": "Vanuatu",
      "tournament": "South Pacific Mini Games",
      "team1": "Vanuatu",
      "team2": "New Caledonia",
      "original_team1": "Vanuatu",
      "original_team2": "New Caledonia",
      "flag1": "vanuatu.png",
      "flag2": "caledonia.png",
      "score1": 1,
      "score2": 1,
      "rating1": 4199.82170065571,
      "rating2": 4614.564600387774,
      "rating_ev": 21.00174033772055,
      "win_prob": 17.9
    },
    {
      "date": "1993-12-07",
      "country": "Vanuatu",
      "tournament": "South Pacific Mini Games",
      "team1": "Vanuatu",
      "team2": "Tonga",
      "original_team1": "Vanuatu",
      "original_team2": "Tonga",
      "flag1": "vanuatu.png",
      "flag2": "tonga.png",
      "score1": 3,
      "score2": 0,
      "rating1": 4178.819960317989,
      "rating2": 3230.9376148662814,
      "rating_ev": -17.82028679463201,
      "win_prob": 98.7
    },
    {
      "date": "1992-09-26",
      "country": "Vanuatu",
      "tournament": "World Cup qualifier",
      "team1": "Vanuatu",
      "team2": "Fiji",
      "original_team1": "Vanuatu",
      "original_team2": "Fiji",
      "flag1": "vanuatu.png",
      "flag2": "fiji.png",
      "score1": 0,
      "score2": 3,
      "rating1": 4196.640247112621,
      "rating2": 4783.176783139658,
      "rating_ev": -14.240829865304477,
      "win_prob": 12.6
    },
    {
      "date": "1992-09-12",
      "country": "Fiji",
      "tournament": "World Cup qualifier",
      "team1": "Vanuatu",
      "team2": "Fiji",
      "original_team1": "Vanuatu",
      "original_team2": "Fiji",
      "flag1": "vanuatu.png",
      "flag2": "fiji.png",
      "score1": 0,
      "score2": 3,
      "rating1": 4210.881076977926,
      "rating2": 4754.022382989347,
      "rating_ev": -4.21879230273953,
      "win_prob": 6.2
    },
    {
      "date": "1992-07-30",
      "country": "Vanuatu",
      "tournament": "Melanesian Cup",
      "team1": "Vanuatu",
      "team2": "Fiji",
      "original_team1": "Vanuatu",
      "original_team2": "Fiji",
      "flag1": "vanuatu.png",
      "flag2": "fiji.png",
      "score1": 0,
      "score2": 2,
      "rating1": 4215.099869280665,
      "rating2": 4749.803590686607,
      "rating_ev": -2.635521658932703,
      "win_prob": 13.9
    },
    {
      "date": "1992-07-27",
      "country": "Vanuatu",
      "tournament": "Melanesian Cup",
      "team1": "Vanuatu",
      "team2": "Solomon Islands",
      "original_team1": "Vanuatu",
      "original_team2": "Solomon Islands",
      "flag1": "vanuatu.png",
      "flag2": "solomon.png",
      "score1": 1,
      "score2": 3,
      "rating1": 4217.735390939598,
      "rating2": 4530.389825633474,
      "rating_ev": -16.748141442329143,
      "win_prob": 31.4
    },
    {
      "date": "1992-07-25",
      "country": "Vanuatu",
      "tournament": "Melanesian Cup",
      "team1": "Vanuatu",
      "team2": "New Caledonia",
      "original_team1": "Vanuatu",
      "original_team2": "New Caledonia",
      "flag1": "vanuatu.png",
      "flag2": "caledonia.png",
      "score1": 0,
      "score2": 1,
      "rating1": 4234.483532381927,
      "rating2": 4635.65302376606,
      "rating_ev": 4.432023044362722,
      "win_prob": 20.9
    },
    {
      "date": "1992-07-20",
      "country": "Vanuatu",
      "tournament": "Friendly",
      "team1": "Vanuatu",
      "team2": "Tahiti",
      "original_team1": "Vanuatu",
      "original_team2": "Tahiti",
      "flag1": "vanuatu.png",
      "flag2": "tahiti.png",
      "score1": 1,
      "score2": 2,
      "rating1": 4230.051509337564,
      "rating2": 4808.938617063019,
      "rating_ev": 7.236825557551128,
      "win_prob": 11.2
    },
    {
      "date": "1992-07-13",
      "country": "Vanuatu",
      "tournament": "Friendly",
      "team1": "Vanuatu",
      "team2": "Tahiti",
      "original_team1": "Vanuatu",
      "original_team2": "Tahiti",
      "flag1": "vanuatu.png",
      "flag2": "tahiti.png",
      "score1": 2,
      "score2": 1,
      "rating1": 4222.814683780013,
      "rating2": 4816.17544262057,
      "rating_ev": 22.365159559181848,
      "win_prob": 9.6
    },
    {
      "date": "1992-07-01",
      "country": "New Zealand",
      "tournament": "World Cup qualifier",
      "team1": "Vanuatu",
      "team2": "New Zealand",
      "original_team1": "Vanuatu",
      "original_team2": "New Zealand",
      "flag1": "vanuatu.png",
      "flag2": "new_zealand.png",
      "score1": 0,
      "score2": 8,
      "rating1": 4200.449524220831,
      "rating2": 5102.975921922927,
      "rating_ev": -41.881104780148235,
      "win_prob": 2.2
    },
    {
      "date": "1992-06-27",
      "country": "Vanuatu",
      "tournament": "World Cup qualifier",
      "team1": "Vanuatu",
      "team2": "New Zealand",
      "original_team1": "Vanuatu",
      "original_team2": "New Zealand",
      "flag1": "vanuatu.png",
      "flag2": "new_zealand.png",
      "score1": 1,
      "score2": 4,
      "rating1": 4242.33062900098,
      "rating2": 5061.094817142779,
      "rating_ev": -1.0855345526852034,
      "win_prob": 5.2
    },
    {
      "date": "1991-09-19",
      "country": "Papua New Guinea",
      "tournament": "South Pacific Games",
      "team1": "Vanuatu",
      "team2": "New Caledonia",
      "original_team1": "Vanuatu",
      "original_team2": "New Caledonia",
      "flag1": "vanuatu.png",
      "flag2": "caledonia.png",
      "score1": 0,
      "score2": 3,
      "rating1": 4243.416163553665,
      "rating2": 4649.297216475798,
      "rating_ev": -19.166448541382124,
      "win_prob": 16.9
    },
    {
      "date": "1991-09-17",
      "country": "Papua New Guinea",
      "tournament": "South Pacific Games",
      "team1": "Vanuatu",
      "team2": "Fiji",
      "original_team1": "Vanuatu",
      "original_team2": "Fiji",
      "flag1": "vanuatu.png",
      "flag2": "fiji.png",
      "score1": 1,
      "score2": 3,
      "rating1": 4262.582612095047,
      "rating2": 4792.4106914235,
      "rating_ev": 3.395116117933867,
      "win_prob": 9.2
    },
    {
      "date": "1991-09-13",
      "country": "Papua New Guinea",
      "tournament": "South Pacific Games",
      "team1": "Vanuatu",
      "team2": "Solomon Islands",
      "original_team1": "Vanuatu",
      "original_team2": "Solomon Islands",
      "flag1": "vanuatu.png",
      "flag2": "solomon.png",
      "score1": 0,
      "score2": 3,
      "rating1": 4259.187495977113,
      "rating2": 4423.405129353711,
      "rating_ev": -35.1839488109963,
      "win_prob": 39.8
    },
    {
      "date": "1991-09-11",
      "country": "Papua New Guinea",
      "tournament": "South Pacific Games",
      "team1": "Vanuatu",
      "team2": "Papua New Guinea",
      "original_team1": "Vanuatu",
      "original_team2": "Papua New Guinea",
      "flag1": "vanuatu.png",
      "flag2": "papua.png",
      "score1": 1,
      "score2": 0,
      "rating1": 4294.371444788109,
      "rating2": 4407.047939131575,
      "rating_ev": 29.855891018438342,
      "win_prob": 23.2
    },
    {
      "date": "1990-11-06",
      "country": "New Caledonia",
      "tournament": "Melanesian Cup",
      "team1": "Vanuatu",
      "team2": "Fiji",
      "original_team1": "Vanuatu",
      "original_team2": "Fiji",
      "flag1": "vanuatu.png",
      "flag2": "fiji.png",
      "score1": 1,
      "score2": 1,
      "rating1": 4264.515553769671,
      "rating2": 4688.792760879064,
      "rating_ev": 27.940021482641896,
      "win_prob": 11.3
    },
    {
      "date": "1990-11-05",
      "country": "New Caledonia",
      "tournament": "Melanesian Cup",
      "team1": "Vanuatu",
      "team2": "Papua New Guinea",
      "original_team1": "Vanuatu",
      "original_team2": "Papua New Guinea",
      "flag1": "vanuatu.png",
      "flag2": "papua.png",
      "score1": 1,
      "score2": 0,
      "rating1": 4236.575532287029,
      "rating2": 4466.205029406613,
      "rating_ev": 31.229904686595546,
      "win_prob": 21.9
    },
    {
      "date": "1990-11-03",
      "country": "New Caledonia",
      "tournament": "Melanesian Cup",
      "team1": "Vanuatu",
      "team2": "Solomon Islands",
      "original_team1": "Vanuatu",
      "original_team2": "Solomon Islands",
      "flag1": "vanuatu.png",
      "flag2": "solomon.png",
      "score1": 1,
      "score2": 1,
      "rating1": 4205.3456276004335,
      "rating2": 4364.254868885757,
      "rating_ev": 10.733335674743103,
      "win_prob": 31.2
    },
    {
      "date": "1990-11-01",
      "country": "New Caledonia",
      "tournament": "Melanesian Cup",
      "team1": "Vanuatu",
      "team2": "New Caledonia",
      "original_team1": "Vanuatu",
      "original_team2": "New Caledonia",
      "flag1": "vanuatu.png",
      "flag2": "caledonia.png",
      "score1": 1,
      "score2": 0,
      "rating1": 4194.61229192569,
      "rating2": 4662.155549935929,
      "rating_ev": 52.561379427578686,
      "win_prob": 5.4
    },
    {
      "date": "1989-11-03",
      "country": "Fiji",
      "tournament": "Melanesian Cup",
      "team1": "Vanuatu",
      "team2": "New Caledonia",
      "original_team1": "Vanuatu",
      "original_team2": "New Caledonia",
      "flag1": "vanuatu.png",
      "flag2": "caledonia.png",
      "score1": 1,
      "score2": 5,
      "rating1": 4142.050912498113,
      "rating2": 4713.637684336375,
      "rating_ev": -22.73492569588325,
      "win_prob": 9.6
    },
    {
      "date": "1989-10-31",
      "country": "Fiji",
      "tournament": "Melanesian Cup",
      "team1": "Vanuatu",
      "team2": "Papua New Guinea",
      "original_team1": "Vanuatu",
      "original_team2": "Papua New Guinea",
      "flag1": "vanuatu.png",
      "flag2": "papua.png",
      "score1": 0,
      "score2": 3,
      "rating1": 4164.785838193996,
      "rating2": 4508.8223297648,
      "rating_ev": -23.18396919847146,
      "win_prob": 21.5
    },
    {
      "date": "1989-10-30",
      "country": "Fiji",
      "tournament": "Melanesian Cup",
      "team1": "Vanuatu",
      "team2": "Fiji",
      "original_team1": "Vanuatu",
      "original_team2": "Fiji",
      "flag1": "vanuatu.png",
      "flag2": "fiji.png",
      "score1": 1,
      "score2": 2,
      "rating1": 4187.969807392467,
      "rating2": 4734.046784207999,
      "rating_ev": 26.006095744300183,
      "win_prob": 4.9
    },
    {
      "date": "1989-10-28",
      "country": "Fiji",
      "tournament": "Melanesian Cup",
      "team1": "Vanuatu",
      "team2": "Solomon Islands",
      "original_team1": "Vanuatu",
      "original_team2": "Solomon Islands",
      "flag1": "vanuatu.png",
      "flag2": "solomon.png",
      "score1": 0,
      "score2": 2,
      "rating1": 4161.963711648167,
      "rating2": 4312.342070198138,
      "rating_ev": -21.190712853874174,
      "win_prob": 38.3
    },
    {
      "date": "1988-10-26",
      "country": "Solomon Islands",
      "tournament": "Melanesian Cup",
      "team1": "Vanuatu",
      "team2": "New Caledonia",
      "original_team1": "Vanuatu",
      "original_team2": "New Caledonia",
      "flag1": "vanuatu.png",
      "flag2": "caledonia.png",
      "score1": 1,
      "score2": 0,
      "rating1": 4183.154424502041,
      "rating2": 4721.904710872679,
      "rating_ev": 50.45275381108331,
      "win_prob": 6.3
    },
    {
      "date": "1988-10-25",
      "country": "Solomon Islands",
      "tournament": "Melanesian Cup",
      "team1": "Vanuatu",
      "team2": "Solomon Islands",
      "original_team1": "Vanuatu",
      "original_team2": "Solomon Islands",
      "flag1": "vanuatu.png",
      "flag2": "solomon.png",
      "score1": 0,
      "score2": 5,
      "rating1": 4132.701670690958,
      "rating2": 4300.810775900988,
      "rating_ev": -55.66534709703774,
      "win_prob": 33.4
    },
    {
      "date": "1988-10-24",
      "country": "Solomon Islands",
      "tournament": "Melanesian Cup",
      "team1": "Vanuatu",
      "team2": "Fiji",
      "original_team1": "Vanuatu",
      "original_team2": "Fiji",
      "flag1": "vanuatu.png",
      "flag2": "fiji.png",
      "score1": 0,
      "score2": 8,
      "rating1": 4188.367017787996,
      "rating2": 4667.509707343337,
      "rating_ev": -73.35919976023251,
      "win_prob": 19.1
    },
    {
      "date": "1988-10-23",
      "country": "Solomon Islands",
      "tournament": "Melanesian Cup",
      "team1": "Vanuatu",
      "team2": "New Caledonia",
      "original_team1": "Vanuatu",
      "original_team2": "New Caledonia",
      "flag1": "vanuatu.png",
      "flag2": "caledonia.png",
      "score1": 1,
      "score2": 6,
      "rating1": 4261.726217548228,
      "rating2": 4853.960800752528,
      "rating_ev": -34.38242601493312,
      "win_prob": 9.7
    },
    {
      "date": "1987-12-19",
      "country": "New Caledonia",
      "tournament": "South Pacific Games",
      "team1": "Vanuatu",
      "team2": "Papua New Guinea",
      "original_team1": "Vanuatu",
      "original_team2": "Papua New Guinea",
      "flag1": "vanuatu.png",
      "flag2": "papua.png",
      "score1": 1,
      "score2": 3,
      "rating1": 4296.108643563161,
      "rating2": 4476.657870149992,
      "rating_ev": -19.156790615239515,
      "win_prob": 34.9
    },
    {
      "date": "1987-12-17",
      "country": "New Caledonia",
      "tournament": "South Pacific Games",
      "team1": "Vanuatu",
      "team2": "New Caledonia",
      "original_team1": "Vanuatu",
      "original_team2": "New Caledonia",
      "flag1": "vanuatu.png",
      "flag2": "caledonia.png",
      "score1": 0,
      "score2": 6,
      "rating1": 4315.265434178401,
      "rating2": 4805.450900946823,
      "rating_ev": -46.21252864074086,
      "win_prob": 10.3
    },
    {
      "date": "1987-12-15",
      "country": "New Caledonia",
      "tournament": "South Pacific Games",
      "team1": "Vanuatu",
      "team2": "Tahiti",
      "original_team1": "Vanuatu",
      "original_team2": "Tahiti",
      "flag1": "vanuatu.png",
      "flag2": "tahiti.png",
      "score1": 1,
      "score2": 2,
      "rating1": 4361.477962819142,
      "rating2": 4902.914410153799,
      "rating_ev": 19.419289985718933,
      "win_prob": 7.9
    },
    {
      "date": "1987-12-12",
      "country": "New Caledonia",
      "tournament": "South Pacific Games",
      "team1": "Vanuatu",
      "team2": "Papua New Guinea",
      "original_team1": "Vanuatu",
      "original_team2": "Papua New Guinea",
      "flag1": "vanuatu.png",
      "flag2": "papua.png",
      "score1": 1,
      "score2": 1,
      "rating1": 4342.058672833423,
      "rating2": 4429.662021531797,
      "rating_ev": 5.934572085127002,
      "win_prob": 39.2
    },
    {
      "date": "1987-12-10",
      "country": "New Caledonia",
      "tournament": "South Pacific Games",
      "team1": "Vanuatu",
      "team2": "Eastern Samoa",
      "original_team1": "Vanuatu",
      "original_team2": "Eastern Samoa",
      "flag1": "vanuatu.png",
      "flag2": "us_samoa.png",
      "score1": 7,
      "score2": 0,
      "rating1": 4336.124100748296,
      "rating2": 2919.129997420083,
      "rating_ev": 16.384970675492696,
      "win_prob": 99.4
    },
    {
      "date": "1983-09-30",
      "country": "Western Samoa",
      "tournament": "South Pacific Games",
      "team1": "Vanuatu",
      "team2": "New Caledonia",
      "original_team1": "Vanuatu",
      "original_team2": "New Caledonia",
      "flag1": "vanuatu.png",
      "flag2": "caledonia.png",
      "score1": 2,
      "score2": 6,
      "rating1": 4319.739130072803,
      "rating2": 4728.6021171553175,
      "rating_ev": -32.98574779786941,
      "win_prob": 18.4
    },
    {
      "date": "1983-08-31",
      "country": "Vanuatu",
      "tournament": "Friendly",
      "team1": "Vanuatu",
      "team2": "Tahiti",
      "original_team1": "Vanuatu",
      "original_team2": "Tahiti",
      "flag1": "vanuatu.png",
      "flag2": "tahiti.png",
      "score1": 1,
      "score2": 1,
      "rating1": 4381.888621968909,
      "rating2": 4988.928612588528,
      "rating_ev": 15.380869901522601,
      "win_prob": 9.6
    },
    {
      "date": "1983-08-31",
      "country": "Vanuatu",
      "tournament": "Friendly",
      "team1": "Vanuatu",
      "team2": "Tahiti",
      "original_team1": "Vanuatu",
      "original_team2": "Tahiti",
      "flag1": "vanuatu.png",
      "flag2": "tahiti.png",
      "score1": 1,
      "score2": 5,
      "rating1": 4369.867327296377,
      "rating2": 5000.949907261061,
      "rating_ev": -12.021294672532349,
      "win_prob": 10.6
    },
    {
      "date": "1983-08-31",
      "country": "Vanuatu",
      "tournament": "Friendly",
      "team1": "Vanuatu",
      "team2": "Tahiti",
      "original_team1": "Vanuatu",
      "original_team2": "Tahiti",
      "flag1": "vanuatu.png",
      "flag2": "tahiti.png",
      "score1": 1,
      "score2": 6,
      "rating1": 4352.724877870673,
      "rating2": 5018.092356686765,
      "rating_ev": -17.1424494257044,
      "win_prob": 9.8
    },
    {
      "date": "1983-08-26",
      "country": "Western Samoa",
      "tournament": "South Pacific Games",
      "team1": "Vanuatu",
      "team2": "Fiji",
      "original_team1": "Vanuatu",
      "original_team2": "Fiji",
      "flag1": "vanuatu.png",
      "flag2": "fiji.png",
      "score1": 0,
      "score2": 6,
      "rating1": 4366.507752067387,
      "rating2": 4518.417302190691,
      "rating_ev": -75.08277260723298,
      "win_prob": 49.8
    },
    {
      "date": "1981-07-15",
      "country": "Solomon Islands",
      "tournament": "South Pacific Mini Games",
      "team1": "Vanuatu",
      "team2": "Papua New Guinea",
      "original_team1": "Vanuatu",
      "original_team2": "Papua New Guinea",
      "flag1": "vanuatu.png",
      "flag2": "papua.png",
      "score1": 0,
      "score2": 1,
      "rating1": 4441.59052467462,
      "rating2": 4225.94528504211,
      "rating_ev": -30.31078007524502,
      "win_prob": 77.0
    },
    {
      "date": "1981-07-13",
      "country": "Solomon Islands",
      "tournament": "South Pacific Mini Games",
      "team1": "Vanuatu",
      "team2": "Papua New Guinea",
      "original_team1": "Vanuatu",
      "original_team2": "Papua New Guinea",
      "flag1": "vanuatu.png",
      "flag2": "papua.png",
      "score1": 2,
      "score2": 3,
      "rating1": 4471.901304749865,
      "rating2": 4170.940991872512,
      "rating_ev": -35.86371262546436,
      "win_prob": 83.4
    },
    {
      "date": "1981-07-11",
      "country": "Solomon Islands",
      "tournament": "South Pacific Mini Games",
      "team1": "Vanuatu",
      "team2": "Solomon Islands",
      "original_team1": "Vanuatu",
      "original_team2": "Solomon Islands",
      "flag1": "vanuatu.png",
      "flag2": "solomon.png",
      "score1": 1,
      "score2": 2,
      "rating1": 4507.765017375329,
      "rating2": 4262.376045245228,
      "rating_ev": -25.882473793079043,
      "win_prob": 70.2
    },
    {
      "date": "1981-07-10",
      "country": "Solomon Islands",
      "tournament": "South Pacific Mini Games",
      "team1": "Vanuatu",
      "team2": "Fiji",
      "original_team1": "Vanuatu",
      "original_team2": "Fiji",
      "flag1": "vanuatu.png",
      "flag2": "fiji.png",
      "score1": 1,
      "score2": 1,
      "rating1": 4533.647491168408,
      "rating2": 4498.399139689211,
      "rating_ev": -2.3904450559039105,
      "win_prob": 54.4
    },
    {
      "date": "1981-07-09",
      "country": "Solomon Islands",
      "tournament": "South Pacific Mini Games",
      "team1": "Vanuatu",
      "team2": "Tahiti",
      "original_team1": "Vanuatu",
      "original_team2": "Tahiti",
      "flag1": "vanuatu.png",
      "flag2": "tahiti.png",
      "score1": 1,
      "score2": 1,
      "rating1": 4536.037936224312,
      "rating2": 4958.934702124879,
      "rating_ev": 27.854329878478893,
      "win_prob": 11.4
    },
    {
      "date": "1981-07-08",
      "country": "Solomon Islands",
      "tournament": "South Pacific Mini Games",
      "team1": "Vanuatu",
      "team2": "New Caledonia",
      "original_team1": "Vanuatu",
      "original_team2": "New Caledonia",
      "flag1": "vanuatu.png",
      "flag2": "caledonia.png",
      "score1": 2,
      "score2": 2,
      "rating1": 4508.183606345833,
      "rating2": 4797.3733723195255,
      "rating_ev": 19.34443066131007,
      "win_prob": 19.4
    },
    {
      "date": "1981-07-07",
      "country": "Solomon Islands",
      "tournament": "South Pacific Mini Games",
      "team1": "Vanuatu",
      "team2": "Samoa",
      "original_team1": "Vanuatu",
      "original_team2": "Western Samoa",
      "flag1": "vanuatu.png",
      "flag2": "samoa.png",
      "score1": 13,
      "score2": 1,
      "rating1": 4488.839175684523,
      "rating2": 2969.47959165716,
      "rating_ev": 29.343967513191274,
      "win_prob": 99.5
    },
    {
      "date": "1980-03-31",
      "country": "Tahiti",
      "tournament": "Friendly",
      "team1": "Vanuatu",
      "team2": "Tahiti",
      "original_team1": "New Hebrides",
      "original_team2": "Tahiti",
      "flag1": "new_hebrides.png",
      "flag2": "tahiti.png",
      "score1": 0,
      "score2": 1,
      "rating1": 4459.495208171332,
      "rating2": 5006.860923108397,
      "rating_ev": 12.308936180323144,
      "win_prob": 5.4
    },
    {
      "date": "1980-02-28",
      "country": "New Caledonia",
      "tournament": "Oceania Nations Cup",
      "team1": "Vanuatu",
      "team2": "Australia",
      "original_team1": "New Hebrides",
      "original_team2": "Australia",
      "flag1": "new_hebrides.png",
      "flag2": "australia.png",
      "score1": 0,
      "score2": 1,
      "rating1": 4447.186271991009,
      "rating2": 5208.846396920786,
      "rating_ev": 31.799166697957844,
      "win_prob": 3.3
    },
    {
      "date": "1980-02-26",
      "country": "New Caledonia",
      "tournament": "Oceania Nations Cup",
      "team1": "Vanuatu",
      "team2": "New Caledonia",
      "original_team1": "New Hebrides",
      "original_team2": "New Caledonia",
      "flag1": "new_hebrides.png",
      "flag2": "caledonia.png",
      "score1": 3,
      "score2": 4,
      "rating1": 4415.387105293051,
      "rating2": 4778.548970841185,
      "rating_ev": 14.729977730660721,
      "win_prob": 10.5
    },
    {
      "date": "1980-02-24",
      "country": "New Caledonia",
      "tournament": "Oceania Nations Cup",
      "team1": "Vanuatu",
      "team2": "Papua New Guinea",
      "original_team1": "New Hebrides",
      "original_team2": "Papua New Guinea",
      "flag1": "new_hebrides.png",
      "flag2": "papua.png",
      "score1": 3,
      "score2": 4,
      "rating1": 4400.65712756239,
      "rating2": 4265.340413515925,
      "rating_ev": -24.97570573570738,
      "win_prob": 69.3
    },
    {
      "date": "1979-09-06",
      "country": "Fiji",
      "tournament": "South Pacific Games",
      "team1": "Vanuatu",
      "team2": "Tonga",
      "original_team1": "New Hebrides",
      "original_team2": "Tonga",
      "flag1": "new_hebrides.png",
      "flag2": "tonga.png",
      "score1": 7,
      "score2": 1,
      "rating1": 4425.6328332980975,
      "rating2": 3221.5167699115254,
      "rating_ev": 14.378308703465336,
      "win_prob": 98.9
    },
    {
      "date": "1979-09-05",
      "country": "Fiji",
      "tournament": "South Pacific Games",
      "team1": "Vanuatu",
      "team2": "Papua New Guinea",
      "original_team1": "New Hebrides",
      "original_team2": "Papua New Guinea",
      "flag1": "new_hebrides.png",
      "flag2": "papua.png",
      "score1": 2,
      "score2": 0,
      "rating1": 4411.254524594632,
      "rating2": 4240.364707780218,
      "rating_ev": 19.807209460234844,
      "win_prob": 64.0
    },
    {
      "date": "1979-09-03",
      "country": "Fiji",
      "tournament": "South Pacific Games",
      "team1": "Vanuatu",
      "team2": "Tahiti",
      "original_team1": "New Hebrides",
      "original_team2": "Tahiti",
      "flag1": "new_hebrides.png",
      "flag2": "tahiti.png",
      "score1": 0,
      "score2": 1,
      "rating1": 4391.447315134397,
      "rating2": 4893.230710798136,
      "rating_ev": 17.032437202239635,
      "win_prob": 9.2
    },
    {
      "date": "1979-08-31",
      "country": "Fiji",
      "tournament": "South Pacific Games",
      "team1": "Vanuatu",
      "team2": "New Caledonia",
      "original_team1": "New Hebrides",
      "original_team2": "New Caledonia",
      "flag1": "new_hebrides.png",
      "flag2": "caledonia.png",
      "score1": 0,
      "score2": 3,
      "rating1": 4374.414877932158,
      "rating2": 4948.732689722635,
      "rating_ev": -8.656200799468024,
      "win_prob": 8.6
    },
    {
      "date": "1979-08-29",
      "country": "Fiji",
      "tournament": "South Pacific Games",
      "team1": "Vanuatu",
      "team2": "Guam",
      "original_team1": "New Hebrides",
      "original_team2": "Guam",
      "flag1": "new_hebrides.png",
      "flag2": "guam.png",
      "score1": 4,
      "score2": 0,
      "rating1": 4383.071078731626,
      "rating2": 3302.696783400109,
      "rating_ev": -4.197450862712685,
      "win_prob": 98.6
    },
    {
      "date": "1979-07-06",
      "country": "Solomon Islands",
      "tournament": "Friendly",
      "team1": "Vanuatu",
      "team2": "Solomon Islands",
      "original_team1": "New Hebrides",
      "original_team2": "Solomon Islands",
      "flag1": "new_hebrides.png",
      "flag2": "solomon.png",
      "score1": 0,
      "score2": 3,
      "rating1": 4387.268529594338,
      "rating2": 4220.754296884775,
      "rating_ev": -23.940386336136726,
      "win_prob": 62.3
    },
    {
      "date": "1979-07-05",
      "country": "Solomon Islands",
      "tournament": "Friendly",
      "team1": "Vanuatu",
      "team2": "Solomon Islands",
      "original_team1": "New Hebrides",
      "original_team2": "Solomon Islands",
      "flag1": "new_hebrides.png",
      "flag2": "solomon.png",
      "score1": 1,
      "score2": 3,
      "rating1": 4411.208915930475,
      "rating2": 4196.813910548638,
      "rating_ev": -18.446079967400692,
      "win_prob": 65.9
    },
    {
      "date": "1978-08-07",
      "country": "New Hebrides",
      "tournament": "Friendly",
      "team1": "Vanuatu",
      "team2": "Tahiti",
      "original_team1": "New Hebrides",
      "original_team2": "Tahiti",
      "flag1": "new_hebrides.png",
      "flag2": "tahiti.png",
      "score1": 2,
      "score2": 4,
      "rating1": 4429.654995897876,
      "rating2": 4865.730378764708,
      "rating_ev": -4.123060139178051,
      "win_prob": 19.7
    },
    {
      "date": "1975-08-05",
      "country": "Guam",
      "tournament": "South Pacific Games",
      "team1": "Vanuatu",
      "team2": "Tahiti",
      "original_team1": "New Hebrides",
      "original_team2": "Tahiti",
      "flag1": "new_hebrides.png",
      "flag2": "tahiti.png",
      "score1": 0,
      "score2": 3,
      "rating1": 4433.778056037054,
      "rating2": 4822.531373576204,
      "rating_ev": -20.271777819708404,
      "win_prob": 18.1
    },
    {
      "date": "1975-08-04",
      "country": "Guam",
      "tournament": "South Pacific Games",
      "team1": "Vanuatu",
      "team2": "New Caledonia",
      "original_team1": "New Hebrides",
      "original_team2": "New Caledonia",
      "flag1": "new_hebrides.png",
      "flag2": "caledonia.png",
      "score1": 1,
      "score2": 3,
      "rating1": 4454.049833856762,
      "rating2": 4967.328782688122,
      "rating_ev": 2.3863850432544496,
      "win_prob": 9.9
    },
    {
      "date": "1975-08-02",
      "country": "Guam",
      "tournament": "South Pacific Games",
      "team1": "Vanuatu",
      "team2": "Papua New Guinea",
      "original_team1": "New Hebrides",
      "original_team2": "Papua New Guinea",
      "flag1": "new_hebrides.png",
      "flag2": "papua.png",
      "score1": 3,
      "score2": 0,
      "rating1": 4451.663448813508,
      "rating2": 4383.397764302387,
      "rating_ev": 41.68602232981357,
      "win_prob": 48.3
    },
    {
      "date": "1973-02-24",
      "country": "New Zealand",
      "tournament": "Oceania Nations Cup",
      "team1": "Vanuatu",
      "team2": "New Caledonia",
      "original_team1": "New Hebrides",
      "original_team2": "New Caledonia",
      "flag1": "new_hebrides.png",
      "flag2": "caledonia.png",
      "score1": 1,
      "score2": 2,
      "rating1": 4409.977426483694,
      "rating2": 4936.121361173534,
      "rating_ev": 18.504039634189212,
      "win_prob": 8.4
    },
    {
      "date": "1973-02-23",
      "country": "New Zealand",
      "tournament": "Oceania Nations Cup",
      "team1": "Vanuatu",
      "team2": "New Zealand",
      "original_team1": "New Hebrides",
      "original_team2": "New Zealand",
      "flag1": "new_hebrides.png",
      "flag2": "new_zealand.png",
      "score1": 1,
      "score2": 3,
      "rating1": 4391.473386849505,
      "rating2": 4876.076476413109,
      "rating_ev": 6.959285002246361,
      "win_prob": 7.1
    },
    {
      "date": "1973-02-21",
      "country": "New Zealand",
      "tournament": "Oceania Nations Cup",
      "team1": "Vanuatu",
      "team2": "Fiji",
      "original_team1": "New Hebrides",
      "original_team2": "Fiji",
      "flag1": "new_hebrides.png",
      "flag2": "fiji.png",
      "score1": 2,
      "score2": 1,
      "rating1": 4384.514101847259,
      "rating2": 4403.992015172672,
      "rating_ev": 17.166490631496345,
      "win_prob": 44.1
    },
    {
      "date": "1973-02-20",
      "country": "New Zealand",
      "tournament": "Oceania Nations Cup",
      "team1": "Vanuatu",
      "team2": "Tahiti",
      "original_team1": "New Hebrides",
      "original_team2": "Tahiti",
      "flag1": "new_hebrides.png",
      "flag2": "tahiti.png",
      "score1": 0,
      "score2": 1,
      "rating1": 4367.347611215762,
      "rating2": 4824.613263501678,
      "rating_ev": 14.30151552741063,
      "win_prob": 11.1
    },
    {
      "date": "1973-02-18",
      "country": "New Zealand",
      "tournament": "Oceania Nations Cup",
      "team1": "Vanuatu",
      "team2": "New Caledonia",
      "original_team1": "New Hebrides",
      "original_team2": "New Caledonia",
      "flag1": "new_hebrides.png",
      "flag2": "caledonia.png",
      "score1": 1,
      "score2": 4,
      "rating1": 4353.046095688352,
      "rating2": 4973.393123272592,
      "rating_ev": -5.914591076573743,
      "win_prob": 7.1
    },
    {
      "date": "1971-09-18",
      "country": "Tahiti",
      "tournament": "South Pacific Games",
      "team1": "Vanuatu",
      "team2": "New Caledonia",
      "original_team1": "New Hebrides",
      "original_team2": "New Caledonia",
      "flag1": "new_hebrides.png",
      "flag2": "caledonia.png",
      "score1": 1,
      "score2": 7,
      "rating1": 4358.960686764925,
      "rating2": 5006.267472389027,
      "rating_ev": -42.80773220623087,
      "win_prob": 8.4
    },
    {
      "date": "1971-09-16",
      "country": "Tahiti",
      "tournament": "South Pacific Games",
      "team1": "Vanuatu",
      "team2": "Tahiti",
      "original_team1": "New Hebrides",
      "original_team2": "Tahiti",
      "flag1": "new_hebrides.png",
      "flag2": "tahiti.png",
      "score1": 2,
      "score2": 1,
      "rating1": 4401.768418971156,
      "rating2": 4793.413425143738,
      "rating_ev": 47.94092609102972,
      "win_prob": 7.4
    },
    {
      "date": "1971-09-13",
      "country": "Tahiti",
      "tournament": "South Pacific Games",
      "team1": "Vanuatu",
      "team2": "New Caledonia",
      "original_team1": "New Hebrides",
      "original_team2": "New Caledonia",
      "flag1": "new_hebrides.png",
      "flag2": "caledonia.png",
      "score1": 0,
      "score2": 0,
      "rating1": 4353.827492880127,
      "rating2": 4934.877789114927,
      "rating_ev": 37.331552910798564,
      "win_prob": 6.0
    },
    {
      "date": "1971-09-11",
      "country": "Tahiti",
      "tournament": "South Pacific Games",
      "team1": "Vanuatu",
      "team2": "Fiji",
      "original_team1": "New Hebrides",
      "original_team2": "Fiji",
      "flag1": "new_hebrides.png",
      "flag2": "fiji.png",
      "score1": 6,
      "score2": 4,
      "rating1": 4316.495939969328,
      "rating2": 4406.060403954176,
      "rating_ev": 37.42190465213025,
      "win_prob": 32.7
    },
    {
      "date": "1969-08-20",
      "country": "Papua New Guinea",
      "tournament": "South Pacific Games",
      "team1": "Vanuatu",
      "team2": "Solomon Islands",
      "original_team1": "New Hebrides",
      "original_team2": "Solomon Islands",
      "flag1": "new_hebrides.png",
      "flag2": "solomon.png",
      "score1": 2,
      "score2": 7,
      "rating1": 4279.074035317198,
      "rating2": 4146.278517258392,
      "rating_ev": -82.2778086729495,
      "win_prob": 78.5
    },
    {
      "date": "1969-08-18",
      "country": "Papua New Guinea",
      "tournament": "South Pacific Games",
      "team1": "Vanuatu",
      "team2": "Papua New Guinea",
      "original_team1": "New Hebrides",
      "original_team2": "Papua New Guinea",
      "flag1": "new_hebrides.png",
      "flag2": "papua.png",
      "score1": 1,
      "score2": 2,
      "rating1": 4361.351843990147,
      "rating2": 4444.864605531367,
      "rating_ev": -3.7788245428700975,
      "win_prob": 31.6
    },
    {
      "date": "1969-08-16",
      "country": "Papua New Guinea",
      "tournament": "South Pacific Games",
      "team1": "Vanuatu",
      "team2": "New Caledonia",
      "original_team1": "New Hebrides",
      "original_team2": "New Caledonia",
      "flag1": "new_hebrides.png",
      "flag2": "caledonia.png",
      "score1": 0,
      "score2": 2,
      "rating1": 4365.130668533017,
      "rating2": 4868.421550677299,
      "rating_ev": 1.7740115197339037,
      "win_prob": 10.3
    },
    {
      "date": "1969-08-15",
      "country": "Papua New Guinea",
      "tournament": "South Pacific Games",
      "team1": "Vanuatu",
      "team2": "Fiji",
      "original_team1": "New Hebrides",
      "original_team2": "Fiji",
      "flag1": "new_hebrides.png",
      "flag2": "fiji.png",
      "score1": 2,
      "score2": 5,
      "rating1": 4363.356657013283,
      "rating2": 4581.946683625555,
      "rating_ev": -31.51868027481578,
      "win_prob": 33.6
    },
    {
      "date": "1969-08-14",
      "country": "Papua New Guinea",
      "tournament": "South Pacific Games",
      "team1": "Vanuatu",
      "team2": "Tahiti",
      "original_team1": "New Hebrides",
      "original_team2": "Tahiti",
      "flag1": "new_hebrides.png",
      "flag2": "tahiti.png",
      "score1": 3,
      "score2": 3,
      "rating1": 4394.875337288099,
      "rating2": 4760.95589448974,
      "rating_ev": 24.286946344402168,
      "win_prob": 14.3
    },
    {
      "date": "1966-12-17",
      "country": "New Caledonia",
      "tournament": "South Pacific Games",
      "team1": "Vanuatu",
      "team2": "Papua New Guinea",
      "original_team1": "New Hebrides",
      "original_team2": "Papua New Guinea",
      "flag1": "new_hebrides.png",
      "flag2": "papua.png",
      "score1": 5,
      "score2": 2,
      "rating1": 4370.588390943697,
      "rating2": 4442.71852738434,
      "rating_ev": 51.16792813107986,
      "win_prob": 31.7
    },
    {
      "date": "1966-12-15",
      "country": "New Caledonia",
      "tournament": "South Pacific Games",
      "team1": "Vanuatu",
      "team2": "Tahiti",
      "original_team1": "New Hebrides",
      "original_team2": "Tahiti",
      "flag1": "new_hebrides.png",
      "flag2": "tahiti.png",
      "score1": 0,
      "score2": 3,
      "rating1": 4319.420462812617,
      "rating2": 4721.684218667818,
      "rating_ev": -19.399396067247835,
      "win_prob": 17.1
    },
    {
      "date": "1966-12-13",
      "country": "New Caledonia",
      "tournament": "South Pacific Games",
      "team1": "Vanuatu",
      "team2": "Solomon Islands",
      "original_team1": "New Hebrides",
      "original_team2": "Solomon Islands",
      "flag1": "new_hebrides.png",
      "flag2": "solomon.png",
      "score1": 4,
      "score2": 4,
      "rating1": 4338.819858879865,
      "rating2": 4126.295765330495,
      "rating_ev": -14.306992294525116,
      "win_prob": 74.2
    },
    {
      "date": "1966-12-12",
      "country": "New Caledonia",
      "tournament": "South Pacific Games",
      "team1": "Vanuatu",
      "team2": "New Caledonia",
      "original_team1": "New Hebrides",
      "original_team2": "New Caledonia",
      "flag1": "new_hebrides.png",
      "flag2": "caledonia.png",
      "score1": 0,
      "score2": 5,
      "rating1": 4353.12685117439,
      "rating2": 4862.998853700741,
      "rating_ev": -33.146395730028416,
      "win_prob": 8.7
    },
    {
      "date": "1963-08-30",
      "country": "Fiji",
      "tournament": "South Pacific Games",
      "team1": "Vanuatu",
      "team2": "Solomon Islands",
      "original_team1": "New Hebrides",
      "original_team2": "Solomon Islands",
      "flag1": "new_hebrides.png",
      "flag2": "solomon.png",
      "score1": 3,
      "score2": 6,
      "rating1": 4386.273246904419,
      "rating2": 4283.234373339842,
      "rating_ev": -53.23437333984202,
      "win_prob": 71.5
    },
    {
      "date": "1957-09-09",
      "country": "Tahiti",
      "tournament": "Friendly",
      "team1": "Vanuatu",
      "team2": "Tahiti",
      "original_team1": "New Hebrides",
      "original_team2": "Tahiti",
      "flag1": "new_hebrides.png",
      "flag2": "tahiti.png",
      "score1": 1,
      "score2": 2,
      "rating1": 4439.507620244261,
      "rating2": 4696.057904170493,
      "rating_ev": 3.661445003227527,
      "win_prob": 16.9
    },
    {
      "date": "1953-09-30",
      "country": "New Hebrides",
      "tournament": "Friendly",
      "team1": "Vanuatu",
      "team2": "Tahiti",
      "original_team1": "New Hebrides",
      "original_team2": "Tahiti",
      "flag1": "new_hebrides.png",
      "flag2": "tahiti.png",
      "score1": 2,
      "score2": 4,
      "rating1": 4435.846175241033,
      "rating2": 4690.273005639133,
      "rating_ev": -9.659914362288873,
      "win_prob": 35.7
    },
    {
      "date": "1951-10-04",
      "country": "New Caledonia",
      "tournament": "Friendly",
      "team1": "Vanuatu",
      "team2": "New Zealand",
      "original_team1": "New Hebrides",
      "original_team2": "New Zealand",
      "flag1": "new_hebrides.png",
      "flag2": "new_zealand.png",
      "score1": 0,
      "score2": 9,
      "rating1": 4445.506089603322,
      "rating2": 4751.553801582571,
      "rating_ev": -43.493910396678075,
      "win_prob": 27.7
    }
  ]
}